{
  "timerange": "20251106-20260203",
  "raw_output": "Result for strategy BTCMomentumScalper\n                                             BACKTESTING REPORT                                              \n\u250f\u2501\u2501\u2501\u2501\u2501\u2501\u2501\u2501\u2501\u2501\u2533\u2501\u2501\u2501\u2501\u2501\u2501\u2501\u2501\u2533\u2501\u2501\u2501\u2501\u2501\u2501\u2501\u2501\u2501\u2501\u2501\u2501\u2501\u2501\u2533\u2501\u2501\u2501\u2501\u2501\u2501\u2501\u2501\u2501\u2501\u2501\u2501\u2501\u2501\u2501\u2501\u2501\u2533\u2501\u2501\u2501\u2501\u2501\u2501\u2501\u2501\u2501\u2501\u2501\u2501\u2501\u2501\u2533\u2501\u2501\u2501\u2501\u2501\u2501\u2501\u2501\u2501\u2501\u2501\u2501\u2501\u2501\u2533\u2501\u2501\u2501\u2501\u2501\u2501\u2501\u2501\u2501\u2501\u2501\u2501\u2501\u2501\u2501\u2501\u2501\u2501\u2501\u2501\u2501\u2501\u2501\u2501\u2513\n\u2503     Pair \u2503 Trades \u2503 Avg Profit % \u2503 Tot Profit USDT \u2503 Tot Profit % \u2503 Avg Duration \u2503  Win  Draw  Loss  Win% \u2503\n\u2521\u2501\u2501\u2501\u2501\u2501\u2501\u2501\u2501\u2501\u2501\u2547\u2501\u2501\u2501\u2501\u2501\u2501\u2501\u2501\u2547\u2501\u2501\u2501\u2501\u2501\u2501\u2501\u2501\u2501\u2501\u2501\u2501\u2501\u2501\u2547\u2501\u2501\u2501\u2501\u2501\u2501\u2501\u2501\u2501\u2501\u2501\u2501\u2501\u2501\u2501\u2501\u2501\u2547\u2501\u2501\u2501\u2501\u2501\u2501\u2501\u2501\u2501\u2501\u2501\u2501\u2501\u2501\u2547\u2501\u2501\u2501\u2501\u2501\u2501\u2501\u2501\u2501\u2501\u2501\u2501\u2501\u2501\u2547\u2501\u2501\u2501\u2501\u2501\u2501\u2501\u2501\u2501\u2501\u2501\u2501\u2501\u2501\u2501\u2501\u2501\u2501\u2501\u2501\u2501\u2501\u2501\u2501\u2529\n\u2502 BTC/USDT \u2502     29 \u2502        -0.51 \u2502        -496.649 \u2502        -4.97 \u2502     15:43:00 \u2502   10    18     1  34.5 \u2502\n\u2502    TOTAL \u2502     29 \u2502        -0.51 \u2502        -496.649 \u2502        -4.97 \u2502     15:43:00 \u2502   10    18     1  34.5 \u2502\n\u2514\u2500\u2500\u2500\u2500\u2500\u2500\u2500\u2500\u2500\u2500\u2534\u2500\u2500\u2500\u2500\u2500\u2500\u2500\u2500\u2534\u2500\u2500\u2500\u2500\u2500\u2500\u2500\u2500\u2500\u2500\u2500\u2500\u2500\u2500\u2534\u2500\u2500\u2500\u2500\u2500\u2500\u2500\u2500\u2500\u2500\u2500\u2500\u2500\u2500\u2500\u2500\u2500\u2534\u2500\u2500\u2500\u2500\u2500\u2500\u2500\u2500\u2500\u2500\u2500\u2500\u2500\u2500\u2534\u2500\u2500\u2500\u2500\u2500\u2500\u2500\u2500\u2500\u2500\u2500\u2500\u2500\u2500\u2534\u2500\u2500\u2500\u2500\u2500\u2500\u2500\u2500\u2500\u2500\u2500\u2500\u2500\u2500\u2500\u2500\u2500\u2500\u2500\u2500\u2500\u2500\u2500\u2500\u2518\n                                         LEFT OPEN TRADES REPORT                                          \n\u250f\u2501\u2501\u2501\u2501\u2501\u2501\u2501\u2533\u2501\u2501\u2501\u2501\u2501\u2501\u2501\u2501\u2533\u2501\u2501\u2501\u2501\u2501\u2501\u2501\u2501\u2501\u2501\u2501\u2501\u2501\u2501\u2533\u2501\u2501\u2501\u2501\u2501\u2501\u2501\u2501\u2501\u2501\u2501\u2501\u2501\u2501\u2501\u2501\u2501\u2533\u2501\u2501\u2501\u2501\u2501\u2501\u2501\u2501\u2501\u2501\u2501\u2501\u2501\u2501\u2533\u2501\u2501\u2501\u2501\u2501\u2501\u2501\u2501\u2501\u2501\u2501\u2501\u2501\u2501\u2533\u2501\u2501\u2501\u2501\u2501\u2501\u2501\u2501\u2501\u2501\u2501\u2501\u2501\u2501\u2501\u2501\u2501\u2501\u2501\u2501\u2501\u2501\u2501\u2501\u2513\n\u2503  Pair \u2503 Trades \u2503 Avg Profit % \u2503 Tot Profit USDT \u2503 Tot Profit % \u2503 Avg Duration \u2503  Win  Draw  Loss  Win% \u2503\n\u2521\u2501\u2501\u2501\u2501\u2501\u2501\u2501\u2547\u2501\u2501\u2501\u2501\u2501\u2501\u2501\u2501\u2547\u2501\u2501\u2501\u2501\u2501\u2501\u2501\u2501\u2501\u2501\u2501\u2501\u2501\u2501\u2547\u2501\u2501\u2501\u2501\u2501\u2501\u2501\u2501\u2501\u2501\u2501\u2501\u2501\u2501\u2501\u2501\u2501\u2547\u2501\u2501\u2501\u2501\u2501\u2501\u2501\u2501\u2501\u2501\u2501\u2501\u2501\u2501\u2547\u2501\u2501\u2501\u2501\u2501\u2501\u2501\u2501\u2501\u2501\u2501\u2501\u2501\u2501\u2547\u2501\u2501\u2501\u2501\u2501\u2501\u2501\u2501\u2501\u2501\u2501\u2501\u2501\u2501\u2501\u2501\u2501\u2501\u2501\u2501\u2501\u2501\u2501\u2501\u2529\n\u2502 TOTAL \u2502      0 \u2502          0.0 \u2502           0.000 \u2502          0.0 \u2502         0:00 \u2502    0     0     0     0 \u2502\n\u2514\u2500\u2500\u2500\u2500\u2500\u2500\u2500\u2534\u2500\u2500\u2500\u2500\u2500\u2500\u2500\u2500\u2534\u2500\u2500\u2500\u2500\u2500\u2500\u2500\u2500\u2500\u2500\u2500\u2500\u2500\u2500\u2534\u2500\u2500\u2500\u2500\u2500\u2500\u2500\u2500\u2500\u2500\u2500\u2500\u2500\u2500\u2500\u2500\u2500\u2534\u2500\u2500\u2500\u2500\u2500\u2500\u2500\u2500\u2500\u2500\u2500\u2500\u2500\u2500\u2534\u2500\u2500\u2500\u2500\u2500\u2500\u2500\u2500\u2500\u2500\u2500\u2500\u2500\u2500\u2534\u2500\u2500\u2500\u2500\u2500\u2500\u2500\u2500\u2500\u2500\u2500\u2500\u2500\u2500\u2500\u2500\u2500\u2500\u2500\u2500\u2500\u2500\u2500\u2500\u2518\n                                                ENTER TAG STATS                                                \n\u250f\u2501\u2501\u2501\u2501\u2501\u2501\u2501\u2501\u2501\u2501\u2501\u2533\u2501\u2501\u2501\u2501\u2501\u2501\u2501\u2501\u2501\u2533\u2501\u2501\u2501\u2501\u2501\u2501\u2501\u2501\u2501\u2501\u2501\u2501\u2501\u2501\u2533\u2501\u2501\u2501\u2501\u2501\u2501\u2501\u2501\u2501\u2501\u2501\u2501\u2501\u2501\u2501\u2501\u2501\u2533\u2501\u2501\u2501\u2501\u2501\u2501\u2501\u2501\u2501\u2501\u2501\u2501\u2501\u2501\u2533\u2501\u2501\u2501\u2501\u2501\u2501\u2501\u2501\u2501\u2501\u2501\u2501\u2501\u2501\u2533\u2501\u2501\u2501\u2501\u2501\u2501\u2501\u2501\u2501\u2501\u2501\u2501\u2501\u2501\u2501\u2501\u2501\u2501\u2501\u2501\u2501\u2501\u2501\u2501\u2513\n\u2503 Enter Tag \u2503 Entries \u2503 Avg Profit % \u2503 Tot Profit USDT \u2503 Tot Profit % \u2503 Avg Duration \u2503  Win  Draw  Loss  Win% \u2503\n\u2521\u2501\u2501\u2501\u2501\u2501\u2501\u2501\u2501\u2501\u2501\u2501\u2547\u2501\u2501\u2501\u2501\u2501\u2501\u2501\u2501\u2501\u2547\u2501\u2501\u2501\u2501\u2501\u2501\u2501\u2501\u2501\u2501\u2501\u2501\u2501\u2501\u2547\u2501\u2501\u2501\u2501\u2501\u2501\u2501\u2501\u2501\u2501\u2501\u2501\u2501\u2501\u2501\u2501\u2501\u2547\u2501\u2501\u2501\u2501\u2501\u2501\u2501\u2501\u2501\u2501\u2501\u2501\u2501\u2501\u2547\u2501\u2501\u2501\u2501\u2501\u2501\u2501\u2501\u2501\u2501\u2501\u2501\u2501\u2501\u2547\u2501\u2501\u2501\u2501\u2501\u2501\u2501\u2501\u2501\u2501\u2501\u2501\u2501\u2501\u2501\u2501\u2501\u2501\u2501\u2501\u2501\u2501\u2501\u2501\u2529\n\u2502     OTHER \u2502      29 \u2502        -0.51 \u2502        -496.649 \u2502        -4.97 \u2502     15:43:00 \u2502   10    18     1  34.5 \u2502\n\u2502     TOTAL \u2502      29 \u2502        -0.51 \u2502        -496.649 \u2502        -4.97 \u2502     15:43:00 \u2502   10    18     1  34.5 \u2502\n\u2514\u2500\u2500\u2500\u2500\u2500\u2500\u2500\u2500\u2500\u2500\u2500\u2534\u2500\u2500\u2500\u2500\u2500\u2500\u2500\u2500\u2500\u2534\u2500\u2500\u2500\u2500\u2500\u2500\u2500\u2500\u2500\u2500\u2500\u2500\u2500\u2500\u2534\u2500\u2500\u2500\u2500\u2500\u2500\u2500\u2500\u2500\u2500\u2500\u2500\u2500\u2500\u2500\u2500\u2500\u2534\u2500\u2500\u2500\u2500\u2500\u2500\u2500\u2500\u2500\u2500\u2500\u2500\u2500\u2500\u2534\u2500\u2500\u2500\u2500\u2500\u2500\u2500\u2500\u2500\u2500\u2500\u2500\u2500\u2500\u2534\u2500\u2500\u2500\u2500\u2500\u2500\u2500\u2500\u2500\u2500\u2500\u2500\u2500\u2500\u2500\u2500\u2500\u2500\u2500\u2500\u2500\u2500\u2500\u2500\u2518\n                                                    EXIT REASON STATS                                                    \n\u250f\u2501\u2501\u2501\u2501\u2501\u2501\u2501\u2501\u2501\u2501\u2501\u2501\u2501\u2501\u2501\u2501\u2501\u2501\u2501\u2501\u2533\u2501\u2501\u2501\u2501\u2501\u2501\u2501\u2533\u2501\u2501\u2501\u2501\u2501\u2501\u2501\u2501\u2501\u2501\u2501\u2501\u2501\u2501\u2533\u2501\u2501\u2501\u2501\u2501\u2501\u2501\u2501\u2501\u2501\u2501\u2501\u2501\u2501\u2501\u2501\u2501\u2533\u2501\u2501\u2501\u2501\u2501\u2501\u2501\u2501\u2501\u2501\u2501\u2501\u2501\u2501\u2533\u2501\u2501\u2501\u2501\u2501\u2501\u2501\u2501\u2501\u2501\u2501\u2501\u2501\u2501\u2501\u2501\u2501\u2533\u2501\u2501\u2501\u2501\u2501\u2501\u2501\u2501\u2501\u2501\u2501\u2501\u2501\u2501\u2501\u2501\u2501\u2501\u2501\u2501\u2501\u2501\u2501\u2501\u2513\n\u2503        Exit Reason \u2503 Exits \u2503 Avg Profit % \u2503 Tot Profit USDT \u2503 Tot Profit % \u2503    Avg Duration \u2503  Win  Draw  Loss  Win% \u2503\n\u2521\u2501\u2501\u2501\u2501\u2501\u2501\u2501\u2501\u2501\u2501\u2501\u2501\u2501\u2501\u2501\u2501\u2501\u2501\u2501\u2501\u2547\u2501\u2501\u2501\u2501\u2501\u2501\u2501\u2547\u2501\u2501\u2501\u2501\u2501\u2501\u2501\u2501\u2501\u2501\u2501\u2501\u2501\u2501\u2547\u2501\u2501\u2501\u2501\u2501\u2501\u2501\u2501\u2501\u2501\u2501\u2501\u2501\u2501\u2501\u2501\u2501\u2547\u2501\u2501\u2501\u2501\u2501\u2501\u2501\u2501\u2501\u2501\u2501\u2501\u2501\u2501\u2547\u2501\u2501\u2501\u2501\u2501\u2501\u2501\u2501\u2501\u2501\u2501\u2501\u2501\u2501\u2501\u2501\u2501\u2547\u2501\u2501\u2501\u2501\u2501\u2501\u2501\u2501\u2501\u2501\u2501\u2501\u2501\u2501\u2501\u2501\u2501\u2501\u2501\u2501\u2501\u2501\u2501\u2501\u2529\n\u2502                roi \u2502    28 \u2502         0.11 \u2502          98.782 \u2502         0.99 \u2502        10:05:00 \u2502   10    18     0   100 \u2502\n\u2502 trailing_stop_loss \u2502     1 \u2502       -18.03 \u2502        -595.431 \u2502        -5.95 \u2502 7 days, 5:20:00 \u2502    0     0     1     0 \u2502\n\u2502              TOTAL \u2502    29 \u2502        -0.51 \u2502        -496.649 \u2502        -4.97 \u2502        15:43:00 \u2502   10    18     1  34.5 \u2502\n\u2514\u2500\u2500\u2500\u2500\u2500\u2500\u2500\u2500\u2500\u2500\u2500\u2500\u2500\u2500\u2500\u2500\u2500\u2500\u2500\u2500\u2534\u2500\u2500\u2500\u2500\u2500\u2500\u2500\u2534\u2500\u2500\u2500\u2500\u2500\u2500\u2500\u2500\u2500\u2500\u2500\u2500\u2500\u2500\u2534\u2500\u2500\u2500\u2500\u2500\u2500\u2500\u2500\u2500\u2500\u2500\u2500\u2500\u2500\u2500\u2500\u2500\u2534\u2500\u2500\u2500\u2500\u2500\u2500\u2500\u2500\u2500\u2500\u2500\u2500\u2500\u2500\u2534\u2500\u2500\u2500\u2500\u2500\u2500\u2500\u2500\u2500\u2500\u2500\u2500\u2500\u2500\u2500\u2500\u2500\u2534\u2500\u2500\u2500\u2500\u2500\u2500\u2500\u2500\u2500\u2500\u2500\u2500\u2500\u2500\u2500\u2500\u2500\u2500\u2500\u2500\u2500\u2500\u2500\u2500\u2518\n                                                           MIXED TAG STATS                                                            \n\u250f\u2501\u2501\u2501\u2501\u2501\u2501\u2501\u2501\u2501\u2501\u2501\u2533\u2501\u2501\u2501\u2501\u2501\u2501\u2501\u2501\u2501\u2501\u2501\u2501\u2501\u2501\u2501\u2501\u2501\u2501\u2501\u2501\u2533\u2501\u2501\u2501\u2501\u2501\u2501\u2501\u2501\u2533\u2501\u2501\u2501\u2501\u2501\u2501\u2501\u2501\u2501\u2501\u2501\u2501\u2501\u2501\u2533\u2501\u2501\u2501\u2501\u2501\u2501\u2501\u2501\u2501\u2501\u2501\u2501\u2501\u2501\u2501\u2501\u2501\u2533\u2501\u2501\u2501\u2501\u2501\u2501\u2501\u2501\u2501\u2501\u2501\u2501\u2501\u2501\u2533\u2501\u2501\u2501\u2501\u2501\u2501\u2501\u2501\u2501\u2501\u2501\u2501\u2501\u2501\u2501\u2501\u2501\u2533\u2501\u2501\u2501\u2501\u2501\u2501\u2501\u2501\u2501\u2501\u2501\u2501\u2501\u2501\u2501\u2501\u2501\u2501\u2501\u2501\u2501\u2501\u2501\u2501\u2513\n\u2503 Enter Tag \u2503        Exit Reason \u2503 Trades \u2503 Avg Profit % \u2503 Tot Profit USDT \u2503 Tot Profit % \u2503    Avg Duration \u2503  Win  Draw  Loss  Win% \u2503\n\u2521\u2501\u2501\u2501\u2501\u2501\u2501\u2501\u2501\u2501\u2501\u2501\u2547\u2501\u2501\u2501\u2501\u2501\u2501\u2501\u2501\u2501\u2501\u2501\u2501\u2501\u2501\u2501\u2501\u2501\u2501\u2501\u2501\u2547\u2501\u2501\u2501\u2501\u2501\u2501\u2501\u2501\u2547\u2501\u2501\u2501\u2501\u2501\u2501\u2501\u2501\u2501\u2501\u2501\u2501\u2501\u2501\u2547\u2501\u2501\u2501\u2501\u2501\u2501\u2501\u2501\u2501\u2501\u2501\u2501\u2501\u2501\u2501\u2501\u2501\u2547\u2501\u2501\u2501\u2501\u2501\u2501\u2501\u2501\u2501\u2501\u2501\u2501\u2501\u2501\u2547\u2501\u2501\u2501\u2501\u2501\u2501\u2501\u2501\u2501\u2501\u2501\u2501\u2501\u2501\u2501\u2501\u2501\u2547\u2501\u2501\u2501\u2501\u2501\u2501\u2501\u2501\u2501\u2501\u2501\u2501\u2501\u2501\u2501\u2501\u2501\u2501\u2501\u2501\u2501\u2501\u2501\u2501\u2529\n\u2502           \u2502                roi \u2502     28 \u2502         0.11 \u2502          98.782 \u2502         0.99 \u2502        10:05:00 \u2502   10    18     0   100 \u2502\n\u2502           \u2502 trailing_stop_loss \u2502      1 \u2502       -18.03 \u2502        -595.431 \u2502        -5.95 \u2502 7 days, 5:20:00 \u2502    0     0     1     0 \u2502\n\u2502     TOTAL \u2502                    \u2502     29 \u2502        -0.51 \u2502        -496.649 \u2502        -4.97 \u2502        15:43:00 \u2502   10    18     1  34.5 \u2502\n\u2514\u2500\u2500\u2500\u2500\u2500\u2500\u2500\u2500\u2500\u2500\u2500\u2534\u2500\u2500\u2500\u2500\u2500\u2500\u2500\u2500\u2500\u2500\u2500\u2500\u2500\u2500\u2500\u2500\u2500\u2500\u2500\u2500\u2534\u2500\u2500\u2500\u2500\u2500\u2500\u2500\u2500\u2534\u2500\u2500\u2500\u2500\u2500\u2500\u2500\u2500\u2500\u2500\u2500\u2500\u2500\u2500\u2534\u2500\u2500\u2500\u2500\u2500\u2500\u2500\u2500\u2500\u2500\u2500\u2500\u2500\u2500\u2500\u2500\u2500\u2534\u2500\u2500\u2500\u2500\u2500\u2500\u2500\u2500\u2500\u2500\u2500\u2500\u2500\u2500\u2534\u2500\u2500\u2500\u2500\u2500\u2500\u2500\u2500\u2500\u2500\u2500\u2500\u2500\u2500\u2500\u2500\u2500\u2534\u2500\u2500\u2500\u2500\u2500\u2500\u2500\u2500\u2500\u2500\u2500\u2500\u2500\u2500\u2500\u2500\u2500\u2500\u2500\u2500\u2500\u2500\u2500\u2500\u2518\n                         SUMMARY METRICS                          \n\u250f\u2501\u2501\u2501\u2501\u2501\u2501\u2501\u2501\u2501\u2501\u2501\u2501\u2501\u2501\u2501\u2501\u2501\u2501\u2501\u2501\u2501\u2501\u2501\u2501\u2501\u2501\u2501\u2501\u2501\u2501\u2501\u2533\u2501\u2501\u2501\u2501\u2501\u2501\u2501\u2501\u2501\u2501\u2501\u2501\u2501\u2501\u2501\u2501\u2501\u2501\u2501\u2501\u2501\u2501\u2501\u2501\u2501\u2501\u2501\u2501\u2501\u2501\u2501\u2501\u2513\n\u2503 Metric                        \u2503 Value                          \u2503\n\u2521\u2501\u2501\u2501\u2501\u2501\u2501\u2501\u2501\u2501\u2501\u2501\u2501\u2501\u2501\u2501\u2501\u2501\u2501\u2501\u2501\u2501\u2501\u2501\u2501\u2501\u2501\u2501\u2501\u2501\u2501\u2501\u2547\u2501\u2501\u2501\u2501\u2501\u2501\u2501\u2501\u2501\u2501\u2501\u2501\u2501\u2501\u2501\u2501\u2501\u2501\u2501\u2501\u2501\u2501\u2501\u2501\u2501\u2501\u2501\u2501\u2501\u2501\u2501\u2501\u2529\n\u2502 Backtesting from              \u2502 2025-11-06 00:00:00            \u2502\n\u2502 Backtesting to                \u2502 2026-02-03 00:00:00            \u2502\n\u2502 Trading Mode                  \u2502 Spot                           \u2502\n\u2502 Max open trades               \u2502 1                              \u2502\n\u2502                               \u2502                                \u2502\n\u2502 Total/Daily Avg Trades        \u2502 29 / 0.33                      \u2502\n\u2502 Starting balance              \u2502 10000 USDT                     \u2502\n\u2502 Final balance                 \u2502 9503.351 USDT                  \u2502\n\u2502 Absolute profit               \u2502 -496.649 USDT                  \u2502\n\u2502 Total profit %                \u2502 -4.97%                         \u2502\n\u2502 CAGR %                        \u2502 -18.85%                        \u2502\n\u2502 Sortino                       \u2502 -100.00                        \u2502\n\u2502 Sharpe                        \u2502 -0.97                          \u2502\n\u2502 Calmar                        \u2502 -17.90                         \u2502\n\u2502 SQN                           \u2502 -0.83                          \u2502\n\u2502 Profit factor                 \u2502 0.17                           \u2502\n\u2502 Expectancy (Ratio)            \u2502 -17.13 (-0.65)                 \u2502\n\u2502 Avg. daily profit             \u2502 -5.58 USDT                     \u2502\n\u2502 Avg. stake amount             \u2502 3125.645 USDT                  \u2502\n\u2502 Total trade volume            \u2502 181152.7 USDT                  \u2502\n\u2502                               \u2502                                \u2502\n\u2502 Best Pair                     \u2502 BTC/USDT -4.97%                \u2502\n\u2502 Worst Pair                    \u2502 BTC/USDT -4.97%                \u2502\n\u2502 Best trade                    \u2502 BTC/USDT 1.56%                 \u2502\n\u2502 Worst trade                   \u2502 BTC/USDT -18.03%               \u2502\n\u2502 Best day                      \u2502 48.671 USDT                    \u2502\n\u2502 Worst day                     \u2502 -595.431 USDT                  \u2502\n\u2502 Days win/draw/lose            \u2502 10 / 73 / 1                    \u2502\n\u2502 Min/Max/Avg. Duration Winners \u2502 0d 01:10 / 0d 01:10 / 0d 01:10 \u2502\n\u2502 Min/Max/Avg. Duration Losers  \u2502 7d 05:20 / 7d 05:20 / 7d 05:20 \u2502\n\u2502 Max Consecutive Wins / Loss   \u2502 2 / 4                          \u2502\n\u2502 Rejected Entry signals        \u2502 0                              \u2502\n\u2502 Entry/Exit Timeouts           \u2502 0 / 0                          \u2502\n\u2502                               \u2502                                \u2502\n\u2502 Min balance                   \u2502 9404.569 USDT                  \u2502\n\u2502 Max balance                   \u2502 10000 USDT                     \u2502\n\u2502 Max % of account underwater   \u2502 5.95%                          \u2502\n\u2502 Absolute drawdown             \u2502 595.431 USDT (5.95%)           \u2502\n\u2502 Drawdown duration             \u2502 10 days 05:05:00               \u2502\n\u2502 Profit at drawdown start      \u2502 0 USDT                         \u2502\n\u2502 Profit at drawdown end        \u2502 -595.431 USDT                  \u2502\n\u2502 Drawdown start                \u2502 2025-11-11 02:25:00            \u2502\n\u2502 Drawdown end                  \u2502 2025-11-21 07:30:00            \u2502\n\u2502 Market change                 \u2502 -24.21%                        \u2502\n\u2514\u2500\u2500\u2500\u2500\u2500\u2500\u2500\u2500\u2500\u2500\u2500\u2500\u2500\u2500\u2500\u2500\u2500\u2500\u2500\u2500\u2500\u2500\u2500\u2500\u2500\u2500\u2500\u2500\u2500\u2500\u2500\u2534\u2500\u2500\u2500\u2500\u2500\u2500\u2500\u2500\u2500\u2500\u2500\u2500\u2500\u2500\u2500\u2500\u2500\u2500\u2500\u2500\u2500\u2500\u2500\u2500\u2500\u2500\u2500\u2500\u2500\u2500\u2500\u2500\u2518\n\nBacktested 2025-11-06 00:00:00 -> 2026-02-03 00:00:00 | Max open trades : 1\n                                                              STRATEGY SUMMARY                                                               \n\u250f\u2501\u2501\u2501\u2501\u2501\u2501\u2501\u2501\u2501\u2501\u2501\u2501\u2501\u2501\u2501\u2501\u2501\u2501\u2501\u2501\u2533\u2501\u2501\u2501\u2501\u2501\u2501\u2501\u2501\u2533\u2501\u2501\u2501\u2501\u2501\u2501\u2501\u2501\u2501\u2501\u2501\u2501\u2501\u2501\u2533\u2501\u2501\u2501\u2501\u2501\u2501\u2501\u2501\u2501\u2501\u2501\u2501\u2501\u2501\u2501\u2501\u2501\u2533\u2501\u2501\u2501\u2501\u2501\u2501\u2501\u2501\u2501\u2501\u2501\u2501\u2501\u2501\u2533\u2501\u2501\u2501\u2501\u2501\u2501\u2501\u2501\u2501\u2501\u2501\u2501\u2501\u2501\u2533\u2501\u2501\u2501\u2501\u2501\u2501\u2501\u2501\u2501\u2501\u2501\u2501\u2501\u2501\u2501\u2501\u2501\u2501\u2501\u2501\u2501\u2501\u2501\u2501\u2533\u2501\u2501\u2501\u2501\u2501\u2501\u2501\u2501\u2501\u2501\u2501\u2501\u2501\u2501\u2501\u2501\u2501\u2501\u2501\u2501\u2501\u2513\n\u2503           Strategy \u2503 Trades \u2503 Avg Profit % \u2503 Tot Profit USDT \u2503 Tot Profit % \u2503 Avg Duration \u2503  Win  Draw  Loss  Win% \u2503            Drawdown \u2503\n\u2521\u2501\u2501\u2501\u2501\u2501\u2501\u2501\u2501\u2501\u2501\u2501\u2501\u2501\u2501\u2501\u2501\u2501\u2501\u2501\u2501\u2547\u2501\u2501\u2501\u2501\u2501\u2501\u2501\u2501\u2547\u2501\u2501\u2501\u2501\u2501\u2501\u2501\u2501\u2501\u2501\u2501\u2501\u2501\u2501\u2547\u2501\u2501\u2501\u2501\u2501\u2501\u2501\u2501\u2501\u2501\u2501\u2501\u2501\u2501\u2501\u2501\u2501\u2547\u2501\u2501\u2501\u2501\u2501\u2501\u2501\u2501\u2501\u2501\u2501\u2501\u2501\u2501\u2547\u2501\u2501\u2501\u2501\u2501\u2501\u2501\u2501\u2501\u2501\u2501\u2501\u2501\u2501\u2547\u2501\u2501\u2501\u2501\u2501\u2501\u2501\u2501\u2501\u2501\u2501\u2501\u2501\u2501\u2501\u2501\u2501\u2501\u2501\u2501\u2501\u2501\u2501\u2501\u2547\u2501\u2501\u2501\u2501\u2501\u2501\u2501\u2501\u2501\u2501\u2501\u2501\u2501\u2501\u2501\u2501\u2501\u2501\u2501\u2501\u2501\u2529\n\u2502 BTCMomentumScalper \u2502     29 \u2502        -0.51 \u2502        -496.649 \u2502        -4.97 \u2502     15:43:00 \u2502   10    18     1  34.5 \u2502 595.431 USDT  5.95% \u2502\n\u2514\u2500\u2500\u2500\u2500\u2500\u2500\u2500\u2500\u2500\u2500\u2500\u2500\u2500\u2500\u2500\u2500\u2500\u2500\u2500\u2500\u2534\u2500\u2500\u2500\u2500\u2500\u2500\u2500\u2500\u2534\u2500\u2500\u2500\u2500\u2500\u2500\u2500\u2500\u2500\u2500\u2500\u2500\u2500\u2500\u2534\u2500\u2500\u2500\u2500\u2500\u2500\u2500\u2500\u2500\u2500\u2500\u2500\u2500\u2500\u2500\u2500\u2500\u2534\u2500\u2500\u2500\u2500\u2500\u2500\u2500\u2500\u2500\u2500\u2500\u2500\u2500\u2500\u2534\u2500\u2500\u2500\u2500\u2500\u2500\u2500\u2500\u2500\u2500\u2500\u2500\u2500\u2500\u2534\u2500\u2500\u2500\u2500\u2500\u2500\u2500\u2500\u2500\u2500\u2500\u2500\u2500\u2500\u2500\u2500\u2500\u2500\u2500\u2500\u2500\u2500\u2500\u2500\u2534\u2500\u2500\u2500\u2500\u2500\u2500\u2500\u2500\u2500\u2500\u2500\u2500\u2500\u2500\u2500\u2500\u2500\u2500\u2500\u2500\u2500\u2518\n2026-02-02 19:42:10,007 - freqtrade - INFO - freqtrade 2026.1\n2026-02-02 19:42:11,292 - freqtrade.configuration.load_config - INFO - Using config: config/config.json ...\n2026-02-02 19:42:11,293 - freqtrade.loggers - INFO - Enabling colorized output.\n2026-02-02 19:42:11,294 - freqtrade.loggers - INFO - Logfile configured\n2026-02-02 19:42:11,294 - freqtrade.loggers - INFO - Verbosity set to 0\n2026-02-02 19:42:11,294 - freqtrade.configuration.configuration - INFO - Using additional Strategy lookup path: strategies/btc_momentum_scalper/\n2026-02-02 19:42:11,294 - freqtrade.configuration.configuration - INFO - Using max_open_trades: 3 ...\n2026-02-02 19:42:11,294 - freqtrade.configuration.configuration - INFO - Parameter --timerange detected: 20251106-20260203 ...\n2026-02-02 19:42:11,295 - freqtrade.configuration.configuration - INFO - Using user-data directory: /Users/naynay/Projects/personal/backtest-strat/user_data ...\n2026-02-02 19:42:11,295 - freqtrade.configuration.configuration - INFO - Using data directory: /Users/naynay/Projects/personal/backtest-strat/user_data/data/bybit ...\n2026-02-02 19:42:11,295 - freqtrade.configuration.configuration - INFO - Parameter --cache=day detected ...\n2026-02-02 19:42:11,295 - freqtrade.configuration.configuration - INFO - Filter trades by timerange: 20251106-20260203\n2026-02-02 19:42:11,296 - freqtrade.exchange.check_exchange - INFO - Checking exchange...\n2026-02-02 19:42:11,300 - freqtrade.exchange.check_exchange - INFO - Exchange \"bybit\" is officially supported by the Freqtrade development team.\n2026-02-02 19:42:11,300 - freqtrade.configuration.configuration - INFO - Using pairlist from configuration.\n2026-02-02 19:42:11,300 - freqtrade.configuration.config_validation - INFO - Validating configuration ...\n2026-02-02 19:42:11,302 - freqtrade.commands.optimize_commands - INFO - Starting freqtrade in Backtesting mode\n2026-02-02 19:42:11,302 - freqtrade.exchange.exchange - INFO - Instance is running with dry_run enabled\n2026-02-02 19:42:11,302 - freqtrade.exchange.exchange - INFO - Using CCXT 4.5.35\n2026-02-02 19:42:11,302 - freqtrade.exchange.exchange - INFO - Applying additional ccxt config: {'options': {'defaultType': 'spot'}}\n2026-02-02 19:42:11,306 - freqtrade.exchange.exchange - INFO - Applying additional ccxt config: {'options': {'defaultType': 'spot'}}\n2026-02-02 19:42:11,309 - freqtrade.exchange.exchange - INFO - Using Exchange \"Bybit\"\n2026-02-02 19:42:13,320 - freqtrade.resolvers.exchange_resolver - INFO - Using resolved exchange 'Bybit'...\n2026-02-02 19:42:13,337 - freqtrade.resolvers.iresolver - INFO - Using resolved strategy BTCMomentumScalper from \n'/Users/naynay/Projects/personal/backtest-strat/strategies/btc_momentum_scalper/strategy.py'...\n2026-02-02 19:42:13,337 - freqtrade.strategy.hyper - INFO - Loading parameters from file /Users/naynay/Projects/personal/backtest-strat/strategies/btc_momentum_scalper/strategy.json\n2026-02-02 19:42:13,337 - freqtrade.resolvers.strategy_resolver - INFO - Override strategy 'stake_currency' with value from the configuration: USDT.\n2026-02-02 19:42:13,338 - freqtrade.resolvers.strategy_resolver - INFO - Override strategy 'stake_amount' with value from the configuration: unlimited.\n2026-02-02 19:42:13,338 - freqtrade.resolvers.strategy_resolver - INFO - Override strategy 'unfilledtimeout' with value from the configuration: {'entry': 10, 'exit': 10, 'exit_timeout_count': 0, \n'unit': 'minutes'}.\n2026-02-02 19:42:13,338 - freqtrade.resolvers.strategy_resolver - INFO - Override strategy 'use_exit_signal' with value from the configuration: False.\n2026-02-02 19:42:13,338 - freqtrade.resolvers.strategy_resolver - INFO - Override strategy 'max_open_trades' with value from the configuration: 3.\n2026-02-02 19:42:13,338 - freqtrade.resolvers.strategy_resolver - INFO - Strategy using minimal_roi: {'0': 0.136, '17': 0.036, '40': 0.022, '70': 0}\n2026-02-02 19:42:13,338 - freqtrade.resolvers.strategy_resolver - INFO - Strategy using timeframe: 5m\n2026-02-02 19:42:13,339 - freqtrade.resolvers.strategy_resolver - INFO - Strategy using stoploss: -0.182\n2026-02-02 19:42:13,339 - freqtrade.resolvers.strategy_resolver - INFO - Strategy using trailing_stop: True\n2026-02-02 19:42:13,339 - freqtrade.resolvers.strategy_resolver - INFO - Strategy using trailing_stop_positive: 0.347\n2026-02-02 19:42:13,339 - freqtrade.resolvers.strategy_resolver - INFO - Strategy using trailing_stop_positive_offset: 0.378\n2026-02-02 19:42:13,339 - freqtrade.resolvers.strategy_resolver - INFO - Strategy using trailing_only_offset_is_reached: False\n2026-02-02 19:42:13,339 - freqtrade.resolvers.strategy_resolver - INFO - Strategy using use_custom_stoploss: False\n2026-02-02 19:42:13,339 - freqtrade.resolvers.strategy_resolver - INFO - Strategy using process_only_new_candles: True\n2026-02-02 19:42:13,340 - freqtrade.resolvers.strategy_resolver - INFO - Strategy using order_types: {'entry': 'limit', 'exit': 'limit', 'stoploss': 'market', 'stoploss_on_exchange': False}\n2026-02-02 19:42:13,340 - freqtrade.resolvers.strategy_resolver - INFO - Strategy using order_time_in_force: {'entry': 'GTC', 'exit': 'GTC'}\n2026-02-02 19:42:13,340 - freqtrade.resolvers.strategy_resolver - INFO - Strategy using stake_currency: USDT\n2026-02-02 19:42:13,340 - freqtrade.resolvers.strategy_resolver - INFO - Strategy using stake_amount: unlimited\n2026-02-02 19:42:13,340 - freqtrade.resolvers.strategy_resolver - INFO - Strategy using startup_candle_count: 30\n2026-02-02 19:42:13,340 - freqtrade.resolvers.strategy_resolver - INFO - Strategy using unfilledtimeout: {'entry': 10, 'exit': 10, 'exit_timeout_count': 0, 'unit': 'minutes'}\n2026-02-02 19:42:13,341 - freqtrade.resolvers.strategy_resolver - INFO - Strategy using use_exit_signal: False\n2026-02-02 19:42:13,341 - freqtrade.resolvers.strategy_resolver - INFO - Strategy using exit_profit_only: False\n2026-02-02 19:42:13,341 - freqtrade.resolvers.strategy_resolver - INFO - Strategy using ignore_roi_if_entry_signal: False\n2026-02-02 19:42:13,341 - freqtrade.resolvers.strategy_resolver - INFO - Strategy using exit_profit_offset: 0.0\n2026-02-02 19:42:13,341 - freqtrade.resolvers.strategy_resolver - INFO - Strategy using disable_dataframe_checks: False\n2026-02-02 19:42:13,341 - freqtrade.resolvers.strategy_resolver - INFO - Strategy using ignore_buying_expired_candle_after: 0\n2026-02-02 19:42:13,342 - freqtrade.resolvers.strategy_resolver - INFO - Strategy using position_adjustment_enable: False\n2026-02-02 19:42:13,342 - freqtrade.resolvers.strategy_resolver - INFO - Strategy using max_entry_position_adjustment: -1\n2026-02-02 19:42:13,342 - freqtrade.resolvers.strategy_resolver - INFO - Strategy using max_open_trades: 3\n2026-02-02 19:42:13,342 - freqtrade.configuration.config_validation - INFO - Validating configuration ...\n2026-02-02 19:42:13,347 - freqtrade.resolvers.iresolver - INFO - Using resolved pairlist StaticPairList from \n'/Users/naynay/Projects/personal/backtest-strat/.venv/lib/python3.11/site-packages/freqtrade/plugins/pairlist/StaticPairList.py'...\n2026-02-02 19:42:13,354 - freqtrade.optimize.backtesting - INFO - Using fee 0.1000% - worst case fee from exchange (lowest tier).\n2026-02-02 19:42:13,445 - freqtrade.optimize.backtesting - INFO - Loading data from 2025-11-05 21:30:00 up to 2026-02-03 00:00:00 (89 days).\n2026-02-02 19:42:13,575 - freqtrade.optimize.backtesting - INFO - Dataload complete. Calculating indicators\n2026-02-02 19:42:13,577 - freqtrade.optimize.backtesting - INFO - Running backtesting for Strategy BTCMomentumScalper\n2026-02-02 19:42:13,577 - freqtrade.strategy.hyper - INFO - Strategy Parameter: buy_ema_long = 22\n2026-02-02 19:42:13,577 - freqtrade.strategy.hyper - INFO - Strategy Parameter: buy_ema_short = 11\n2026-02-02 19:42:13,578 - freqtrade.strategy.hyper - INFO - Strategy Parameter: buy_rsi_max = 76\n2026-02-02 19:42:13,578 - freqtrade.strategy.hyper - INFO - Strategy Parameter: buy_volume_factor = 0.7\n2026-02-02 19:42:13,578 - freqtrade.strategy.hyper - INFO - Strategy Parameter: sell_rsi_max = 80\n2026-02-02 19:42:13,584 - freqtrade.optimize.backtesting - INFO - Backtesting with data from 2025-11-06 00:00:00 up to 2026-02-03 00:00:00 (89 days).\n2026-02-02 19:42:14,191 - freqtrade.misc - INFO - dumping json to \"/Users/naynay/Projects/personal/backtest-strat/user_data/backtest_results/backtest-result-2026-02-02_19-42-14.meta.json\"\n",
  "market_change": "-24.21%",
  "trades": "29",
  "avg_profit_pct": "-0.51",
  "total_profit_usdt": "-496.649",
  "total_profit_pct": "-4.97",
  "avg_duration": "15:43:00",
  "win_draw_loss": "10    18     1  34.5",
  "drawdown": "595.431 USDT  5.95%",
  "name": "last_90d"
}