{
  "timerange": "20250202-20260203",
  "raw_output": "Result for strategy BTCMomentumScalper\n                                              BACKTESTING REPORT                                               \n\u250f\u2501\u2501\u2501\u2501\u2501\u2501\u2501\u2501\u2501\u2501\u2533\u2501\u2501\u2501\u2501\u2501\u2501\u2501\u2501\u2533\u2501\u2501\u2501\u2501\u2501\u2501\u2501\u2501\u2501\u2501\u2501\u2501\u2501\u2501\u2533\u2501\u2501\u2501\u2501\u2501\u2501\u2501\u2501\u2501\u2501\u2501\u2501\u2501\u2501\u2501\u2501\u2501\u2533\u2501\u2501\u2501\u2501\u2501\u2501\u2501\u2501\u2501\u2501\u2501\u2501\u2501\u2501\u2533\u2501\u2501\u2501\u2501\u2501\u2501\u2501\u2501\u2501\u2501\u2501\u2501\u2501\u2501\u2501\u2501\u2533\u2501\u2501\u2501\u2501\u2501\u2501\u2501\u2501\u2501\u2501\u2501\u2501\u2501\u2501\u2501\u2501\u2501\u2501\u2501\u2501\u2501\u2501\u2501\u2501\u2513\n\u2503     Pair \u2503 Trades \u2503 Avg Profit % \u2503 Tot Profit USDT \u2503 Tot Profit % \u2503   Avg Duration \u2503  Win  Draw  Loss  Win% \u2503\n\u2521\u2501\u2501\u2501\u2501\u2501\u2501\u2501\u2501\u2501\u2501\u2547\u2501\u2501\u2501\u2501\u2501\u2501\u2501\u2501\u2547\u2501\u2501\u2501\u2501\u2501\u2501\u2501\u2501\u2501\u2501\u2501\u2501\u2501\u2501\u2547\u2501\u2501\u2501\u2501\u2501\u2501\u2501\u2501\u2501\u2501\u2501\u2501\u2501\u2501\u2501\u2501\u2501\u2547\u2501\u2501\u2501\u2501\u2501\u2501\u2501\u2501\u2501\u2501\u2501\u2501\u2501\u2501\u2547\u2501\u2501\u2501\u2501\u2501\u2501\u2501\u2501\u2501\u2501\u2501\u2501\u2501\u2501\u2501\u2501\u2547\u2501\u2501\u2501\u2501\u2501\u2501\u2501\u2501\u2501\u2501\u2501\u2501\u2501\u2501\u2501\u2501\u2501\u2501\u2501\u2501\u2501\u2501\u2501\u2501\u2529\n\u2502 BTC/USDT \u2502     73 \u2502         0.11 \u2502         259.662 \u2502          2.6 \u2502 1 day, 3:12:00 \u2502   21    52     0   100 \u2502\n\u2502    TOTAL \u2502     73 \u2502         0.11 \u2502         259.662 \u2502          2.6 \u2502 1 day, 3:12:00 \u2502   21    52     0   100 \u2502\n\u2514\u2500\u2500\u2500\u2500\u2500\u2500\u2500\u2500\u2500\u2500\u2534\u2500\u2500\u2500\u2500\u2500\u2500\u2500\u2500\u2534\u2500\u2500\u2500\u2500\u2500\u2500\u2500\u2500\u2500\u2500\u2500\u2500\u2500\u2500\u2534\u2500\u2500\u2500\u2500\u2500\u2500\u2500\u2500\u2500\u2500\u2500\u2500\u2500\u2500\u2500\u2500\u2500\u2534\u2500\u2500\u2500\u2500\u2500\u2500\u2500\u2500\u2500\u2500\u2500\u2500\u2500\u2500\u2534\u2500\u2500\u2500\u2500\u2500\u2500\u2500\u2500\u2500\u2500\u2500\u2500\u2500\u2500\u2500\u2500\u2534\u2500\u2500\u2500\u2500\u2500\u2500\u2500\u2500\u2500\u2500\u2500\u2500\u2500\u2500\u2500\u2500\u2500\u2500\u2500\u2500\u2500\u2500\u2500\u2500\u2518\n                                         LEFT OPEN TRADES REPORT                                          \n\u250f\u2501\u2501\u2501\u2501\u2501\u2501\u2501\u2533\u2501\u2501\u2501\u2501\u2501\u2501\u2501\u2501\u2533\u2501\u2501\u2501\u2501\u2501\u2501\u2501\u2501\u2501\u2501\u2501\u2501\u2501\u2501\u2533\u2501\u2501\u2501\u2501\u2501\u2501\u2501\u2501\u2501\u2501\u2501\u2501\u2501\u2501\u2501\u2501\u2501\u2533\u2501\u2501\u2501\u2501\u2501\u2501\u2501\u2501\u2501\u2501\u2501\u2501\u2501\u2501\u2533\u2501\u2501\u2501\u2501\u2501\u2501\u2501\u2501\u2501\u2501\u2501\u2501\u2501\u2501\u2533\u2501\u2501\u2501\u2501\u2501\u2501\u2501\u2501\u2501\u2501\u2501\u2501\u2501\u2501\u2501\u2501\u2501\u2501\u2501\u2501\u2501\u2501\u2501\u2501\u2513\n\u2503  Pair \u2503 Trades \u2503 Avg Profit % \u2503 Tot Profit USDT \u2503 Tot Profit % \u2503 Avg Duration \u2503  Win  Draw  Loss  Win% \u2503\n\u2521\u2501\u2501\u2501\u2501\u2501\u2501\u2501\u2547\u2501\u2501\u2501\u2501\u2501\u2501\u2501\u2501\u2547\u2501\u2501\u2501\u2501\u2501\u2501\u2501\u2501\u2501\u2501\u2501\u2501\u2501\u2501\u2547\u2501\u2501\u2501\u2501\u2501\u2501\u2501\u2501\u2501\u2501\u2501\u2501\u2501\u2501\u2501\u2501\u2501\u2547\u2501\u2501\u2501\u2501\u2501\u2501\u2501\u2501\u2501\u2501\u2501\u2501\u2501\u2501\u2547\u2501\u2501\u2501\u2501\u2501\u2501\u2501\u2501\u2501\u2501\u2501\u2501\u2501\u2501\u2547\u2501\u2501\u2501\u2501\u2501\u2501\u2501\u2501\u2501\u2501\u2501\u2501\u2501\u2501\u2501\u2501\u2501\u2501\u2501\u2501\u2501\u2501\u2501\u2501\u2529\n\u2502 TOTAL \u2502      0 \u2502          0.0 \u2502           0.000 \u2502          0.0 \u2502         0:00 \u2502    0     0     0     0 \u2502\n\u2514\u2500\u2500\u2500\u2500\u2500\u2500\u2500\u2534\u2500\u2500\u2500\u2500\u2500\u2500\u2500\u2500\u2534\u2500\u2500\u2500\u2500\u2500\u2500\u2500\u2500\u2500\u2500\u2500\u2500\u2500\u2500\u2534\u2500\u2500\u2500\u2500\u2500\u2500\u2500\u2500\u2500\u2500\u2500\u2500\u2500\u2500\u2500\u2500\u2500\u2534\u2500\u2500\u2500\u2500\u2500\u2500\u2500\u2500\u2500\u2500\u2500\u2500\u2500\u2500\u2534\u2500\u2500\u2500\u2500\u2500\u2500\u2500\u2500\u2500\u2500\u2500\u2500\u2500\u2500\u2534\u2500\u2500\u2500\u2500\u2500\u2500\u2500\u2500\u2500\u2500\u2500\u2500\u2500\u2500\u2500\u2500\u2500\u2500\u2500\u2500\u2500\u2500\u2500\u2500\u2518\n                                                 ENTER TAG STATS                                                 \n\u250f\u2501\u2501\u2501\u2501\u2501\u2501\u2501\u2501\u2501\u2501\u2501\u2533\u2501\u2501\u2501\u2501\u2501\u2501\u2501\u2501\u2501\u2533\u2501\u2501\u2501\u2501\u2501\u2501\u2501\u2501\u2501\u2501\u2501\u2501\u2501\u2501\u2533\u2501\u2501\u2501\u2501\u2501\u2501\u2501\u2501\u2501\u2501\u2501\u2501\u2501\u2501\u2501\u2501\u2501\u2533\u2501\u2501\u2501\u2501\u2501\u2501\u2501\u2501\u2501\u2501\u2501\u2501\u2501\u2501\u2533\u2501\u2501\u2501\u2501\u2501\u2501\u2501\u2501\u2501\u2501\u2501\u2501\u2501\u2501\u2501\u2501\u2533\u2501\u2501\u2501\u2501\u2501\u2501\u2501\u2501\u2501\u2501\u2501\u2501\u2501\u2501\u2501\u2501\u2501\u2501\u2501\u2501\u2501\u2501\u2501\u2501\u2513\n\u2503 Enter Tag \u2503 Entries \u2503 Avg Profit % \u2503 Tot Profit USDT \u2503 Tot Profit % \u2503   Avg Duration \u2503  Win  Draw  Loss  Win% \u2503\n\u2521\u2501\u2501\u2501\u2501\u2501\u2501\u2501\u2501\u2501\u2501\u2501\u2547\u2501\u2501\u2501\u2501\u2501\u2501\u2501\u2501\u2501\u2547\u2501\u2501\u2501\u2501\u2501\u2501\u2501\u2501\u2501\u2501\u2501\u2501\u2501\u2501\u2547\u2501\u2501\u2501\u2501\u2501\u2501\u2501\u2501\u2501\u2501\u2501\u2501\u2501\u2501\u2501\u2501\u2501\u2547\u2501\u2501\u2501\u2501\u2501\u2501\u2501\u2501\u2501\u2501\u2501\u2501\u2501\u2501\u2547\u2501\u2501\u2501\u2501\u2501\u2501\u2501\u2501\u2501\u2501\u2501\u2501\u2501\u2501\u2501\u2501\u2547\u2501\u2501\u2501\u2501\u2501\u2501\u2501\u2501\u2501\u2501\u2501\u2501\u2501\u2501\u2501\u2501\u2501\u2501\u2501\u2501\u2501\u2501\u2501\u2501\u2529\n\u2502     OTHER \u2502      73 \u2502         0.11 \u2502         259.662 \u2502          2.6 \u2502 1 day, 3:12:00 \u2502   21    52     0   100 \u2502\n\u2502     TOTAL \u2502      73 \u2502         0.11 \u2502         259.662 \u2502          2.6 \u2502 1 day, 3:12:00 \u2502   21    52     0   100 \u2502\n\u2514\u2500\u2500\u2500\u2500\u2500\u2500\u2500\u2500\u2500\u2500\u2500\u2534\u2500\u2500\u2500\u2500\u2500\u2500\u2500\u2500\u2500\u2534\u2500\u2500\u2500\u2500\u2500\u2500\u2500\u2500\u2500\u2500\u2500\u2500\u2500\u2500\u2534\u2500\u2500\u2500\u2500\u2500\u2500\u2500\u2500\u2500\u2500\u2500\u2500\u2500\u2500\u2500\u2500\u2500\u2534\u2500\u2500\u2500\u2500\u2500\u2500\u2500\u2500\u2500\u2500\u2500\u2500\u2500\u2500\u2534\u2500\u2500\u2500\u2500\u2500\u2500\u2500\u2500\u2500\u2500\u2500\u2500\u2500\u2500\u2500\u2500\u2534\u2500\u2500\u2500\u2500\u2500\u2500\u2500\u2500\u2500\u2500\u2500\u2500\u2500\u2500\u2500\u2500\u2500\u2500\u2500\u2500\u2500\u2500\u2500\u2500\u2518\n                                                EXIT REASON STATS                                                \n\u250f\u2501\u2501\u2501\u2501\u2501\u2501\u2501\u2501\u2501\u2501\u2501\u2501\u2501\u2533\u2501\u2501\u2501\u2501\u2501\u2501\u2501\u2533\u2501\u2501\u2501\u2501\u2501\u2501\u2501\u2501\u2501\u2501\u2501\u2501\u2501\u2501\u2533\u2501\u2501\u2501\u2501\u2501\u2501\u2501\u2501\u2501\u2501\u2501\u2501\u2501\u2501\u2501\u2501\u2501\u2533\u2501\u2501\u2501\u2501\u2501\u2501\u2501\u2501\u2501\u2501\u2501\u2501\u2501\u2501\u2533\u2501\u2501\u2501\u2501\u2501\u2501\u2501\u2501\u2501\u2501\u2501\u2501\u2501\u2501\u2501\u2501\u2533\u2501\u2501\u2501\u2501\u2501\u2501\u2501\u2501\u2501\u2501\u2501\u2501\u2501\u2501\u2501\u2501\u2501\u2501\u2501\u2501\u2501\u2501\u2501\u2501\u2513\n\u2503 Exit Reason \u2503 Exits \u2503 Avg Profit % \u2503 Tot Profit USDT \u2503 Tot Profit % \u2503   Avg Duration \u2503  Win  Draw  Loss  Win% \u2503\n\u2521\u2501\u2501\u2501\u2501\u2501\u2501\u2501\u2501\u2501\u2501\u2501\u2501\u2501\u2547\u2501\u2501\u2501\u2501\u2501\u2501\u2501\u2547\u2501\u2501\u2501\u2501\u2501\u2501\u2501\u2501\u2501\u2501\u2501\u2501\u2501\u2501\u2547\u2501\u2501\u2501\u2501\u2501\u2501\u2501\u2501\u2501\u2501\u2501\u2501\u2501\u2501\u2501\u2501\u2501\u2547\u2501\u2501\u2501\u2501\u2501\u2501\u2501\u2501\u2501\u2501\u2501\u2501\u2501\u2501\u2547\u2501\u2501\u2501\u2501\u2501\u2501\u2501\u2501\u2501\u2501\u2501\u2501\u2501\u2501\u2501\u2501\u2547\u2501\u2501\u2501\u2501\u2501\u2501\u2501\u2501\u2501\u2501\u2501\u2501\u2501\u2501\u2501\u2501\u2501\u2501\u2501\u2501\u2501\u2501\u2501\u2501\u2529\n\u2502         roi \u2502    73 \u2502         0.11 \u2502         259.662 \u2502          2.6 \u2502 1 day, 3:12:00 \u2502   21    52     0   100 \u2502\n\u2502       TOTAL \u2502    73 \u2502         0.11 \u2502         259.662 \u2502          2.6 \u2502 1 day, 3:12:00 \u2502   21    52     0   100 \u2502\n\u2514\u2500\u2500\u2500\u2500\u2500\u2500\u2500\u2500\u2500\u2500\u2500\u2500\u2500\u2534\u2500\u2500\u2500\u2500\u2500\u2500\u2500\u2534\u2500\u2500\u2500\u2500\u2500\u2500\u2500\u2500\u2500\u2500\u2500\u2500\u2500\u2500\u2534\u2500\u2500\u2500\u2500\u2500\u2500\u2500\u2500\u2500\u2500\u2500\u2500\u2500\u2500\u2500\u2500\u2500\u2534\u2500\u2500\u2500\u2500\u2500\u2500\u2500\u2500\u2500\u2500\u2500\u2500\u2500\u2500\u2534\u2500\u2500\u2500\u2500\u2500\u2500\u2500\u2500\u2500\u2500\u2500\u2500\u2500\u2500\u2500\u2500\u2534\u2500\u2500\u2500\u2500\u2500\u2500\u2500\u2500\u2500\u2500\u2500\u2500\u2500\u2500\u2500\u2500\u2500\u2500\u2500\u2500\u2500\u2500\u2500\u2500\u2518\n                                                       MIXED TAG STATS                                                        \n\u250f\u2501\u2501\u2501\u2501\u2501\u2501\u2501\u2501\u2501\u2501\u2501\u2533\u2501\u2501\u2501\u2501\u2501\u2501\u2501\u2501\u2501\u2501\u2501\u2501\u2501\u2533\u2501\u2501\u2501\u2501\u2501\u2501\u2501\u2501\u2533\u2501\u2501\u2501\u2501\u2501\u2501\u2501\u2501\u2501\u2501\u2501\u2501\u2501\u2501\u2533\u2501\u2501\u2501\u2501\u2501\u2501\u2501\u2501\u2501\u2501\u2501\u2501\u2501\u2501\u2501\u2501\u2501\u2533\u2501\u2501\u2501\u2501\u2501\u2501\u2501\u2501\u2501\u2501\u2501\u2501\u2501\u2501\u2533\u2501\u2501\u2501\u2501\u2501\u2501\u2501\u2501\u2501\u2501\u2501\u2501\u2501\u2501\u2501\u2501\u2533\u2501\u2501\u2501\u2501\u2501\u2501\u2501\u2501\u2501\u2501\u2501\u2501\u2501\u2501\u2501\u2501\u2501\u2501\u2501\u2501\u2501\u2501\u2501\u2501\u2513\n\u2503 Enter Tag \u2503 Exit Reason \u2503 Trades \u2503 Avg Profit % \u2503 Tot Profit USDT \u2503 Tot Profit % \u2503   Avg Duration \u2503  Win  Draw  Loss  Win% \u2503\n\u2521\u2501\u2501\u2501\u2501\u2501\u2501\u2501\u2501\u2501\u2501\u2501\u2547\u2501\u2501\u2501\u2501\u2501\u2501\u2501\u2501\u2501\u2501\u2501\u2501\u2501\u2547\u2501\u2501\u2501\u2501\u2501\u2501\u2501\u2501\u2547\u2501\u2501\u2501\u2501\u2501\u2501\u2501\u2501\u2501\u2501\u2501\u2501\u2501\u2501\u2547\u2501\u2501\u2501\u2501\u2501\u2501\u2501\u2501\u2501\u2501\u2501\u2501\u2501\u2501\u2501\u2501\u2501\u2547\u2501\u2501\u2501\u2501\u2501\u2501\u2501\u2501\u2501\u2501\u2501\u2501\u2501\u2501\u2547\u2501\u2501\u2501\u2501\u2501\u2501\u2501\u2501\u2501\u2501\u2501\u2501\u2501\u2501\u2501\u2501\u2547\u2501\u2501\u2501\u2501\u2501\u2501\u2501\u2501\u2501\u2501\u2501\u2501\u2501\u2501\u2501\u2501\u2501\u2501\u2501\u2501\u2501\u2501\u2501\u2501\u2529\n\u2502           \u2502         roi \u2502     73 \u2502         0.11 \u2502         259.662 \u2502          2.6 \u2502 1 day, 3:12:00 \u2502   21    52     0   100 \u2502\n\u2502     TOTAL \u2502             \u2502     73 \u2502         0.11 \u2502         259.662 \u2502          2.6 \u2502 1 day, 3:12:00 \u2502   21    52     0   100 \u2502\n\u2514\u2500\u2500\u2500\u2500\u2500\u2500\u2500\u2500\u2500\u2500\u2500\u2534\u2500\u2500\u2500\u2500\u2500\u2500\u2500\u2500\u2500\u2500\u2500\u2500\u2500\u2534\u2500\u2500\u2500\u2500\u2500\u2500\u2500\u2500\u2534\u2500\u2500\u2500\u2500\u2500\u2500\u2500\u2500\u2500\u2500\u2500\u2500\u2500\u2500\u2534\u2500\u2500\u2500\u2500\u2500\u2500\u2500\u2500\u2500\u2500\u2500\u2500\u2500\u2500\u2500\u2500\u2500\u2534\u2500\u2500\u2500\u2500\u2500\u2500\u2500\u2500\u2500\u2500\u2500\u2500\u2500\u2500\u2534\u2500\u2500\u2500\u2500\u2500\u2500\u2500\u2500\u2500\u2500\u2500\u2500\u2500\u2500\u2500\u2500\u2534\u2500\u2500\u2500\u2500\u2500\u2500\u2500\u2500\u2500\u2500\u2500\u2500\u2500\u2500\u2500\u2500\u2500\u2500\u2500\u2500\u2500\u2500\u2500\u2500\u2518\n                         SUMMARY METRICS                          \n\u250f\u2501\u2501\u2501\u2501\u2501\u2501\u2501\u2501\u2501\u2501\u2501\u2501\u2501\u2501\u2501\u2501\u2501\u2501\u2501\u2501\u2501\u2501\u2501\u2501\u2501\u2501\u2501\u2501\u2501\u2501\u2501\u2533\u2501\u2501\u2501\u2501\u2501\u2501\u2501\u2501\u2501\u2501\u2501\u2501\u2501\u2501\u2501\u2501\u2501\u2501\u2501\u2501\u2501\u2501\u2501\u2501\u2501\u2501\u2501\u2501\u2501\u2501\u2501\u2501\u2513\n\u2503 Metric                        \u2503 Value                          \u2503\n\u2521\u2501\u2501\u2501\u2501\u2501\u2501\u2501\u2501\u2501\u2501\u2501\u2501\u2501\u2501\u2501\u2501\u2501\u2501\u2501\u2501\u2501\u2501\u2501\u2501\u2501\u2501\u2501\u2501\u2501\u2501\u2501\u2547\u2501\u2501\u2501\u2501\u2501\u2501\u2501\u2501\u2501\u2501\u2501\u2501\u2501\u2501\u2501\u2501\u2501\u2501\u2501\u2501\u2501\u2501\u2501\u2501\u2501\u2501\u2501\u2501\u2501\u2501\u2501\u2501\u2529\n\u2502 Backtesting from              \u2502 2025-02-02 02:30:00            \u2502\n\u2502 Backtesting to                \u2502 2026-02-03 00:00:00            \u2502\n\u2502 Trading Mode                  \u2502 Spot                           \u2502\n\u2502 Max open trades               \u2502 1                              \u2502\n\u2502                               \u2502                                \u2502\n\u2502 Total/Daily Avg Trades        \u2502 73 / 0.2                       \u2502\n\u2502 Starting balance              \u2502 10000 USDT                     \u2502\n\u2502 Final balance                 \u2502 10259.662 USDT                 \u2502\n\u2502 Absolute profit               \u2502 259.662 USDT                   \u2502\n\u2502 Total profit %                \u2502 2.60%                          \u2502\n\u2502 CAGR %                        \u2502 2.60%                          \u2502\n\u2502 Sortino                       \u2502 -100.00                        \u2502\n\u2502 Sharpe                        \u2502 1.82                           \u2502\n\u2502 Calmar                        \u2502 -100.00                        \u2502\n\u2502 SQN                           \u2502 4.03                           \u2502\n\u2502 Profit factor                 \u2502 0.00                           \u2502\n\u2502 Expectancy (Ratio)            \u2502 3.56 (100.00)                  \u2502\n\u2502 Avg. daily profit             \u2502 0.711 USDT                     \u2502\n\u2502 Avg. stake amount             \u2502 3340.882 USDT                  \u2502\n\u2502 Total trade volume            \u2502 489005.54 USDT                 \u2502\n\u2502                               \u2502                                \u2502\n\u2502 Best Pair                     \u2502 BTC/USDT 2.60%                 \u2502\n\u2502 Worst Pair                    \u2502 BTC/USDT 2.60%                 \u2502\n\u2502 Best trade                    \u2502 BTC/USDT 0.95%                 \u2502\n\u2502 Worst trade                   \u2502 BTC/USDT 0.00%                 \u2502\n\u2502 Best day                      \u2502 56.121 USDT                    \u2502\n\u2502 Worst day                     \u2502 0 USDT                         \u2502\n\u2502 Days win/draw/lose            \u2502 20 / 328 / 0                   \u2502\n\u2502 Min/Max/Avg. Duration Winners \u2502 0d 02:05 / 0d 02:05 / 0d 02:05 \u2502\n\u2502 Min/Max/Avg. Duration Losers  \u2502 0d 00:00 / 0d 00:00 / 0d 00:00 \u2502\n\u2502 Max Consecutive Wins / Loss   \u2502 3 / 10                         \u2502\n\u2502 Rejected Entry signals        \u2502 0                              \u2502\n\u2502 Entry/Exit Timeouts           \u2502 0 / 0                          \u2502\n\u2502                               \u2502                                \u2502\n\u2502 Min balance                   \u2502 10000.451 USDT                 \u2502\n\u2502 Max balance                   \u2502 10259.662 USDT                 \u2502\n\u2502 Max % of account underwater   \u2502 0.00%                          \u2502\n\u2502 Absolute drawdown             \u2502 0 USDT (0.00%)                 \u2502\n\u2502 Drawdown duration             \u2502 0 days 00:00:00                \u2502\n\u2502 Profit at drawdown start      \u2502 0 USDT                         \u2502\n\u2502 Profit at drawdown end        \u2502 0 USDT                         \u2502\n\u2502 Drawdown start                \u2502 2025-02-10 01:20:00            \u2502\n\u2502 Drawdown end                  \u2502 2025-02-10 01:20:00            \u2502\n\u2502 Market change                 \u2502 -22.14%                        \u2502\n\u2514\u2500\u2500\u2500\u2500\u2500\u2500\u2500\u2500\u2500\u2500\u2500\u2500\u2500\u2500\u2500\u2500\u2500\u2500\u2500\u2500\u2500\u2500\u2500\u2500\u2500\u2500\u2500\u2500\u2500\u2500\u2500\u2534\u2500\u2500\u2500\u2500\u2500\u2500\u2500\u2500\u2500\u2500\u2500\u2500\u2500\u2500\u2500\u2500\u2500\u2500\u2500\u2500\u2500\u2500\u2500\u2500\u2500\u2500\u2500\u2500\u2500\u2500\u2500\u2500\u2518\n\nBacktested 2025-02-02 02:30:00 -> 2026-02-03 00:00:00 | Max open trades : 1\n                                                            STRATEGY SUMMARY                                                             \n\u250f\u2501\u2501\u2501\u2501\u2501\u2501\u2501\u2501\u2501\u2501\u2501\u2501\u2501\u2501\u2501\u2501\u2501\u2501\u2501\u2501\u2533\u2501\u2501\u2501\u2501\u2501\u2501\u2501\u2501\u2533\u2501\u2501\u2501\u2501\u2501\u2501\u2501\u2501\u2501\u2501\u2501\u2501\u2501\u2501\u2533\u2501\u2501\u2501\u2501\u2501\u2501\u2501\u2501\u2501\u2501\u2501\u2501\u2501\u2501\u2501\u2501\u2501\u2533\u2501\u2501\u2501\u2501\u2501\u2501\u2501\u2501\u2501\u2501\u2501\u2501\u2501\u2501\u2533\u2501\u2501\u2501\u2501\u2501\u2501\u2501\u2501\u2501\u2501\u2501\u2501\u2501\u2501\u2501\u2501\u2533\u2501\u2501\u2501\u2501\u2501\u2501\u2501\u2501\u2501\u2501\u2501\u2501\u2501\u2501\u2501\u2501\u2501\u2501\u2501\u2501\u2501\u2501\u2501\u2501\u2533\u2501\u2501\u2501\u2501\u2501\u2501\u2501\u2501\u2501\u2501\u2501\u2501\u2501\u2501\u2501\u2513\n\u2503           Strategy \u2503 Trades \u2503 Avg Profit % \u2503 Tot Profit USDT \u2503 Tot Profit % \u2503   Avg Duration \u2503  Win  Draw  Loss  Win% \u2503      Drawdown \u2503\n\u2521\u2501\u2501\u2501\u2501\u2501\u2501\u2501\u2501\u2501\u2501\u2501\u2501\u2501\u2501\u2501\u2501\u2501\u2501\u2501\u2501\u2547\u2501\u2501\u2501\u2501\u2501\u2501\u2501\u2501\u2547\u2501\u2501\u2501\u2501\u2501\u2501\u2501\u2501\u2501\u2501\u2501\u2501\u2501\u2501\u2547\u2501\u2501\u2501\u2501\u2501\u2501\u2501\u2501\u2501\u2501\u2501\u2501\u2501\u2501\u2501\u2501\u2501\u2547\u2501\u2501\u2501\u2501\u2501\u2501\u2501\u2501\u2501\u2501\u2501\u2501\u2501\u2501\u2547\u2501\u2501\u2501\u2501\u2501\u2501\u2501\u2501\u2501\u2501\u2501\u2501\u2501\u2501\u2501\u2501\u2547\u2501\u2501\u2501\u2501\u2501\u2501\u2501\u2501\u2501\u2501\u2501\u2501\u2501\u2501\u2501\u2501\u2501\u2501\u2501\u2501\u2501\u2501\u2501\u2501\u2547\u2501\u2501\u2501\u2501\u2501\u2501\u2501\u2501\u2501\u2501\u2501\u2501\u2501\u2501\u2501\u2529\n\u2502 BTCMomentumScalper \u2502     73 \u2502         0.11 \u2502         259.662 \u2502          2.6 \u2502 1 day, 3:12:00 \u2502   21    52     0   100 \u2502 0 USDT  0.00% \u2502\n\u2514\u2500\u2500\u2500\u2500\u2500\u2500\u2500\u2500\u2500\u2500\u2500\u2500\u2500\u2500\u2500\u2500\u2500\u2500\u2500\u2500\u2534\u2500\u2500\u2500\u2500\u2500\u2500\u2500\u2500\u2534\u2500\u2500\u2500\u2500\u2500\u2500\u2500\u2500\u2500\u2500\u2500\u2500\u2500\u2500\u2534\u2500\u2500\u2500\u2500\u2500\u2500\u2500\u2500\u2500\u2500\u2500\u2500\u2500\u2500\u2500\u2500\u2500\u2534\u2500\u2500\u2500\u2500\u2500\u2500\u2500\u2500\u2500\u2500\u2500\u2500\u2500\u2500\u2534\u2500\u2500\u2500\u2500\u2500\u2500\u2500\u2500\u2500\u2500\u2500\u2500\u2500\u2500\u2500\u2500\u2534\u2500\u2500\u2500\u2500\u2500\u2500\u2500\u2500\u2500\u2500\u2500\u2500\u2500\u2500\u2500\u2500\u2500\u2500\u2500\u2500\u2500\u2500\u2500\u2500\u2534\u2500\u2500\u2500\u2500\u2500\u2500\u2500\u2500\u2500\u2500\u2500\u2500\u2500\u2500\u2500\u2518\n2026-02-02 19:46:47,868 - freqtrade - INFO - freqtrade 2026.1\n2026-02-02 19:46:49,443 - freqtrade.configuration.load_config - INFO - Using config: config/config.json ...\n2026-02-02 19:46:49,446 - freqtrade.loggers - INFO - Enabling colorized output.\n2026-02-02 19:46:49,446 - freqtrade.loggers - INFO - Logfile configured\n2026-02-02 19:46:49,446 - freqtrade.loggers - INFO - Verbosity set to 0\n2026-02-02 19:46:49,447 - freqtrade.configuration.configuration - INFO - Using additional Strategy lookup path: strategies/btc_momentum_scalper/\n2026-02-02 19:46:49,447 - freqtrade.configuration.configuration - INFO - Using max_open_trades: 3 ...\n2026-02-02 19:46:49,447 - freqtrade.configuration.configuration - INFO - Parameter --timerange detected: 20250202-20260203 ...\n2026-02-02 19:46:49,447 - freqtrade.configuration.configuration - INFO - Using user-data directory: /Users/naynay/Projects/personal/backtest-strat/user_data ...\n2026-02-02 19:46:49,448 - freqtrade.configuration.configuration - INFO - Using data directory: /Users/naynay/Projects/personal/backtest-strat/user_data/data/bybit ...\n2026-02-02 19:46:49,448 - freqtrade.configuration.configuration - INFO - Parameter --cache=day detected ...\n2026-02-02 19:46:49,448 - freqtrade.configuration.configuration - INFO - Filter trades by timerange: 20250202-20260203\n2026-02-02 19:46:49,449 - freqtrade.exchange.check_exchange - INFO - Checking exchange...\n2026-02-02 19:46:49,453 - freqtrade.exchange.check_exchange - INFO - Exchange \"bybit\" is officially supported by the Freqtrade development team.\n2026-02-02 19:46:49,453 - freqtrade.configuration.configuration - INFO - Using pairlist from configuration.\n2026-02-02 19:46:49,453 - freqtrade.configuration.config_validation - INFO - Validating configuration ...\n2026-02-02 19:46:49,455 - freqtrade.commands.optimize_commands - INFO - Starting freqtrade in Backtesting mode\n2026-02-02 19:46:49,455 - freqtrade.exchange.exchange - INFO - Instance is running with dry_run enabled\n2026-02-02 19:46:49,456 - freqtrade.exchange.exchange - INFO - Using CCXT 4.5.35\n2026-02-02 19:46:49,456 - freqtrade.exchange.exchange - INFO - Applying additional ccxt config: {'options': {'defaultType': 'spot'}}\n2026-02-02 19:46:49,459 - freqtrade.exchange.exchange - INFO - Applying additional ccxt config: {'options': {'defaultType': 'spot'}}\n2026-02-02 19:46:49,463 - freqtrade.exchange.exchange - INFO - Using Exchange \"Bybit\"\n2026-02-02 19:46:51,341 - freqtrade.resolvers.exchange_resolver - INFO - Using resolved exchange 'Bybit'...\n2026-02-02 19:46:51,363 - freqtrade.resolvers.iresolver - INFO - Using resolved strategy BTCMomentumScalper from \n'/Users/naynay/Projects/personal/backtest-strat/strategies/btc_momentum_scalper/strategy.py'...\n2026-02-02 19:46:51,363 - freqtrade.strategy.hyper - INFO - Loading parameters from file /Users/naynay/Projects/personal/backtest-strat/strategies/btc_momentum_scalper/strategy.json\n2026-02-02 19:46:51,364 - freqtrade.resolvers.strategy_resolver - INFO - Override strategy 'stake_currency' with value from the configuration: USDT.\n2026-02-02 19:46:51,364 - freqtrade.resolvers.strategy_resolver - INFO - Override strategy 'stake_amount' with value from the configuration: unlimited.\n2026-02-02 19:46:51,365 - freqtrade.resolvers.strategy_resolver - INFO - Override strategy 'unfilledtimeout' with value from the configuration: {'entry': 10, 'exit': 10, 'exit_timeout_count': 0, \n'unit': 'minutes'}.\n2026-02-02 19:46:51,365 - freqtrade.resolvers.strategy_resolver - INFO - Override strategy 'use_exit_signal' with value from the configuration: False.\n2026-02-02 19:46:51,365 - freqtrade.resolvers.strategy_resolver - INFO - Override strategy 'max_open_trades' with value from the configuration: 3.\n2026-02-02 19:46:51,365 - freqtrade.resolvers.strategy_resolver - INFO - Strategy using minimal_roi: {'0': 0.271, '38': 0.078, '82': 0.016, '125': 0}\n2026-02-02 19:46:51,365 - freqtrade.resolvers.strategy_resolver - INFO - Strategy using timeframe: 5m\n2026-02-02 19:46:51,365 - freqtrade.resolvers.strategy_resolver - INFO - Strategy using stoploss: -0.301\n2026-02-02 19:46:51,366 - freqtrade.resolvers.strategy_resolver - INFO - Strategy using trailing_stop: True\n2026-02-02 19:46:51,366 - freqtrade.resolvers.strategy_resolver - INFO - Strategy using trailing_stop_positive: 0.288\n2026-02-02 19:46:51,366 - freqtrade.resolvers.strategy_resolver - INFO - Strategy using trailing_stop_positive_offset: 0.339\n2026-02-02 19:46:51,366 - freqtrade.resolvers.strategy_resolver - INFO - Strategy using trailing_only_offset_is_reached: False\n2026-02-02 19:46:51,366 - freqtrade.resolvers.strategy_resolver - INFO - Strategy using use_custom_stoploss: False\n2026-02-02 19:46:51,366 - freqtrade.resolvers.strategy_resolver - INFO - Strategy using process_only_new_candles: True\n2026-02-02 19:46:51,366 - freqtrade.resolvers.strategy_resolver - INFO - Strategy using order_types: {'entry': 'limit', 'exit': 'limit', 'stoploss': 'market', 'stoploss_on_exchange': False}\n2026-02-02 19:46:51,366 - freqtrade.resolvers.strategy_resolver - INFO - Strategy using order_time_in_force: {'entry': 'GTC', 'exit': 'GTC'}\n2026-02-02 19:46:51,367 - freqtrade.resolvers.strategy_resolver - INFO - Strategy using stake_currency: USDT\n2026-02-02 19:46:51,367 - freqtrade.resolvers.strategy_resolver - INFO - Strategy using stake_amount: unlimited\n2026-02-02 19:46:51,367 - freqtrade.resolvers.strategy_resolver - INFO - Strategy using startup_candle_count: 30\n2026-02-02 19:46:51,367 - freqtrade.resolvers.strategy_resolver - INFO - Strategy using unfilledtimeout: {'entry': 10, 'exit': 10, 'exit_timeout_count': 0, 'unit': 'minutes'}\n2026-02-02 19:46:51,367 - freqtrade.resolvers.strategy_resolver - INFO - Strategy using use_exit_signal: False\n2026-02-02 19:46:51,368 - freqtrade.resolvers.strategy_resolver - INFO - Strategy using exit_profit_only: False\n2026-02-02 19:46:51,368 - freqtrade.resolvers.strategy_resolver - INFO - Strategy using ignore_roi_if_entry_signal: False\n2026-02-02 19:46:51,368 - freqtrade.resolvers.strategy_resolver - INFO - Strategy using exit_profit_offset: 0.0\n2026-02-02 19:46:51,368 - freqtrade.resolvers.strategy_resolver - INFO - Strategy using disable_dataframe_checks: False\n2026-02-02 19:46:51,368 - freqtrade.resolvers.strategy_resolver - INFO - Strategy using ignore_buying_expired_candle_after: 0\n2026-02-02 19:46:51,368 - freqtrade.resolvers.strategy_resolver - INFO - Strategy using position_adjustment_enable: False\n2026-02-02 19:46:51,368 - freqtrade.resolvers.strategy_resolver - INFO - Strategy using max_entry_position_adjustment: -1\n2026-02-02 19:46:51,369 - freqtrade.resolvers.strategy_resolver - INFO - Strategy using max_open_trades: 3\n2026-02-02 19:46:51,369 - freqtrade.configuration.config_validation - INFO - Validating configuration ...\n2026-02-02 19:46:51,375 - freqtrade.resolvers.iresolver - INFO - Using resolved pairlist StaticPairList from \n'/Users/naynay/Projects/personal/backtest-strat/.venv/lib/python3.11/site-packages/freqtrade/plugins/pairlist/StaticPairList.py'...\n2026-02-02 19:46:51,379 - freqtrade.optimize.backtesting - INFO - Using fee 0.1000% - worst case fee from exchange (lowest tier).\n2026-02-02 19:46:51,518 - freqtrade.data.history.datahandlers.idatahandler - WARNING - BTC/USDT, spot, 5m, data starts at 2025-02-02 00:00:00\n2026-02-02 19:46:51,563 - freqtrade.optimize.backtesting - INFO - Loading data from 2025-02-02 00:00:00 up to 2026-02-03 00:00:00 (366 days).\n2026-02-02 19:46:51,563 - freqtrade.configuration.timerange - WARNING - Moving start-date by 30 candles to account for startup time.\n2026-02-02 19:46:52,100 - freqtrade.optimize.backtesting - INFO - Dataload complete. Calculating indicators\n2026-02-02 19:46:52,103 - freqtrade.optimize.backtesting - INFO - Running backtesting for Strategy BTCMomentumScalper\n2026-02-02 19:46:52,103 - freqtrade.strategy.hyper - INFO - Strategy Parameter: buy_ema_long = 30\n2026-02-02 19:46:52,103 - freqtrade.strategy.hyper - INFO - Strategy Parameter: buy_ema_short = 15\n2026-02-02 19:46:52,103 - freqtrade.strategy.hyper - INFO - Strategy Parameter: buy_rsi_max = 76\n2026-02-02 19:46:52,104 - freqtrade.strategy.hyper - INFO - Strategy Parameter: buy_volume_factor = 0.8\n2026-02-02 19:46:52,104 - freqtrade.strategy.hyper - INFO - Strategy Parameter: sell_rsi_max = 80\n2026-02-02 19:46:52,123 - freqtrade.optimize.backtesting - INFO - Backtesting with data from 2025-02-02 02:30:00 up to 2026-02-03 00:00:00 (365 days).\n2026-02-02 19:46:53,811 - freqtrade.misc - INFO - dumping json to \"/Users/naynay/Projects/personal/backtest-strat/user_data/backtest_results/backtest-result-2026-02-02_19-46-53.meta.json\"\n",
  "market_change": "-22.14%",
  "trades": "73",
  "avg_profit_pct": "0.11",
  "total_profit_usdt": "259.662",
  "total_profit_pct": "2.6",
  "avg_duration": "1 day, 3:12:00",
  "win_draw_loss": "21    52     0   100",
  "drawdown": "0 USDT  0.00%",
  "name": "all_data_1yr"
}