{
  "timerange": "20250202-20260203",
  "raw_output": "Result for strategy BTCMomentumScalper\n                                             BACKTESTING REPORT                                              \n\u250f\u2501\u2501\u2501\u2501\u2501\u2501\u2501\u2501\u2501\u2501\u2533\u2501\u2501\u2501\u2501\u2501\u2501\u2501\u2501\u2533\u2501\u2501\u2501\u2501\u2501\u2501\u2501\u2501\u2501\u2501\u2501\u2501\u2501\u2501\u2533\u2501\u2501\u2501\u2501\u2501\u2501\u2501\u2501\u2501\u2501\u2501\u2501\u2501\u2501\u2501\u2501\u2501\u2533\u2501\u2501\u2501\u2501\u2501\u2501\u2501\u2501\u2501\u2501\u2501\u2501\u2501\u2501\u2533\u2501\u2501\u2501\u2501\u2501\u2501\u2501\u2501\u2501\u2501\u2501\u2501\u2501\u2501\u2533\u2501\u2501\u2501\u2501\u2501\u2501\u2501\u2501\u2501\u2501\u2501\u2501\u2501\u2501\u2501\u2501\u2501\u2501\u2501\u2501\u2501\u2501\u2501\u2501\u2513\n\u2503     Pair \u2503 Trades \u2503 Avg Profit % \u2503 Tot Profit USDT \u2503 Tot Profit % \u2503 Avg Duration \u2503  Win  Draw  Loss  Win% \u2503\n\u2521\u2501\u2501\u2501\u2501\u2501\u2501\u2501\u2501\u2501\u2501\u2547\u2501\u2501\u2501\u2501\u2501\u2501\u2501\u2501\u2547\u2501\u2501\u2501\u2501\u2501\u2501\u2501\u2501\u2501\u2501\u2501\u2501\u2501\u2501\u2547\u2501\u2501\u2501\u2501\u2501\u2501\u2501\u2501\u2501\u2501\u2501\u2501\u2501\u2501\u2501\u2501\u2501\u2547\u2501\u2501\u2501\u2501\u2501\u2501\u2501\u2501\u2501\u2501\u2501\u2501\u2501\u2501\u2547\u2501\u2501\u2501\u2501\u2501\u2501\u2501\u2501\u2501\u2501\u2501\u2501\u2501\u2501\u2547\u2501\u2501\u2501\u2501\u2501\u2501\u2501\u2501\u2501\u2501\u2501\u2501\u2501\u2501\u2501\u2501\u2501\u2501\u2501\u2501\u2501\u2501\u2501\u2501\u2529\n\u2502 BTC/USDT \u2502     44 \u2502         -0.1 \u2502        -146.442 \u2502        -1.46 \u2502      4:20:00 \u2502   14    26     4  31.8 \u2502\n\u2502    TOTAL \u2502     44 \u2502         -0.1 \u2502        -146.442 \u2502        -1.46 \u2502      4:20:00 \u2502   14    26     4  31.8 \u2502\n\u2514\u2500\u2500\u2500\u2500\u2500\u2500\u2500\u2500\u2500\u2500\u2534\u2500\u2500\u2500\u2500\u2500\u2500\u2500\u2500\u2534\u2500\u2500\u2500\u2500\u2500\u2500\u2500\u2500\u2500\u2500\u2500\u2500\u2500\u2500\u2534\u2500\u2500\u2500\u2500\u2500\u2500\u2500\u2500\u2500\u2500\u2500\u2500\u2500\u2500\u2500\u2500\u2500\u2534\u2500\u2500\u2500\u2500\u2500\u2500\u2500\u2500\u2500\u2500\u2500\u2500\u2500\u2500\u2534\u2500\u2500\u2500\u2500\u2500\u2500\u2500\u2500\u2500\u2500\u2500\u2500\u2500\u2500\u2534\u2500\u2500\u2500\u2500\u2500\u2500\u2500\u2500\u2500\u2500\u2500\u2500\u2500\u2500\u2500\u2500\u2500\u2500\u2500\u2500\u2500\u2500\u2500\u2500\u2518\n                                         LEFT OPEN TRADES REPORT                                          \n\u250f\u2501\u2501\u2501\u2501\u2501\u2501\u2501\u2533\u2501\u2501\u2501\u2501\u2501\u2501\u2501\u2501\u2533\u2501\u2501\u2501\u2501\u2501\u2501\u2501\u2501\u2501\u2501\u2501\u2501\u2501\u2501\u2533\u2501\u2501\u2501\u2501\u2501\u2501\u2501\u2501\u2501\u2501\u2501\u2501\u2501\u2501\u2501\u2501\u2501\u2533\u2501\u2501\u2501\u2501\u2501\u2501\u2501\u2501\u2501\u2501\u2501\u2501\u2501\u2501\u2533\u2501\u2501\u2501\u2501\u2501\u2501\u2501\u2501\u2501\u2501\u2501\u2501\u2501\u2501\u2533\u2501\u2501\u2501\u2501\u2501\u2501\u2501\u2501\u2501\u2501\u2501\u2501\u2501\u2501\u2501\u2501\u2501\u2501\u2501\u2501\u2501\u2501\u2501\u2501\u2513\n\u2503  Pair \u2503 Trades \u2503 Avg Profit % \u2503 Tot Profit USDT \u2503 Tot Profit % \u2503 Avg Duration \u2503  Win  Draw  Loss  Win% \u2503\n\u2521\u2501\u2501\u2501\u2501\u2501\u2501\u2501\u2547\u2501\u2501\u2501\u2501\u2501\u2501\u2501\u2501\u2547\u2501\u2501\u2501\u2501\u2501\u2501\u2501\u2501\u2501\u2501\u2501\u2501\u2501\u2501\u2547\u2501\u2501\u2501\u2501\u2501\u2501\u2501\u2501\u2501\u2501\u2501\u2501\u2501\u2501\u2501\u2501\u2501\u2547\u2501\u2501\u2501\u2501\u2501\u2501\u2501\u2501\u2501\u2501\u2501\u2501\u2501\u2501\u2547\u2501\u2501\u2501\u2501\u2501\u2501\u2501\u2501\u2501\u2501\u2501\u2501\u2501\u2501\u2547\u2501\u2501\u2501\u2501\u2501\u2501\u2501\u2501\u2501\u2501\u2501\u2501\u2501\u2501\u2501\u2501\u2501\u2501\u2501\u2501\u2501\u2501\u2501\u2501\u2529\n\u2502 TOTAL \u2502      0 \u2502          0.0 \u2502           0.000 \u2502          0.0 \u2502         0:00 \u2502    0     0     0     0 \u2502\n\u2514\u2500\u2500\u2500\u2500\u2500\u2500\u2500\u2534\u2500\u2500\u2500\u2500\u2500\u2500\u2500\u2500\u2534\u2500\u2500\u2500\u2500\u2500\u2500\u2500\u2500\u2500\u2500\u2500\u2500\u2500\u2500\u2534\u2500\u2500\u2500\u2500\u2500\u2500\u2500\u2500\u2500\u2500\u2500\u2500\u2500\u2500\u2500\u2500\u2500\u2534\u2500\u2500\u2500\u2500\u2500\u2500\u2500\u2500\u2500\u2500\u2500\u2500\u2500\u2500\u2534\u2500\u2500\u2500\u2500\u2500\u2500\u2500\u2500\u2500\u2500\u2500\u2500\u2500\u2500\u2534\u2500\u2500\u2500\u2500\u2500\u2500\u2500\u2500\u2500\u2500\u2500\u2500\u2500\u2500\u2500\u2500\u2500\u2500\u2500\u2500\u2500\u2500\u2500\u2500\u2518\n                                                ENTER TAG STATS                                                \n\u250f\u2501\u2501\u2501\u2501\u2501\u2501\u2501\u2501\u2501\u2501\u2501\u2533\u2501\u2501\u2501\u2501\u2501\u2501\u2501\u2501\u2501\u2533\u2501\u2501\u2501\u2501\u2501\u2501\u2501\u2501\u2501\u2501\u2501\u2501\u2501\u2501\u2533\u2501\u2501\u2501\u2501\u2501\u2501\u2501\u2501\u2501\u2501\u2501\u2501\u2501\u2501\u2501\u2501\u2501\u2533\u2501\u2501\u2501\u2501\u2501\u2501\u2501\u2501\u2501\u2501\u2501\u2501\u2501\u2501\u2533\u2501\u2501\u2501\u2501\u2501\u2501\u2501\u2501\u2501\u2501\u2501\u2501\u2501\u2501\u2533\u2501\u2501\u2501\u2501\u2501\u2501\u2501\u2501\u2501\u2501\u2501\u2501\u2501\u2501\u2501\u2501\u2501\u2501\u2501\u2501\u2501\u2501\u2501\u2501\u2513\n\u2503 Enter Tag \u2503 Entries \u2503 Avg Profit % \u2503 Tot Profit USDT \u2503 Tot Profit % \u2503 Avg Duration \u2503  Win  Draw  Loss  Win% \u2503\n\u2521\u2501\u2501\u2501\u2501\u2501\u2501\u2501\u2501\u2501\u2501\u2501\u2547\u2501\u2501\u2501\u2501\u2501\u2501\u2501\u2501\u2501\u2547\u2501\u2501\u2501\u2501\u2501\u2501\u2501\u2501\u2501\u2501\u2501\u2501\u2501\u2501\u2547\u2501\u2501\u2501\u2501\u2501\u2501\u2501\u2501\u2501\u2501\u2501\u2501\u2501\u2501\u2501\u2501\u2501\u2547\u2501\u2501\u2501\u2501\u2501\u2501\u2501\u2501\u2501\u2501\u2501\u2501\u2501\u2501\u2547\u2501\u2501\u2501\u2501\u2501\u2501\u2501\u2501\u2501\u2501\u2501\u2501\u2501\u2501\u2547\u2501\u2501\u2501\u2501\u2501\u2501\u2501\u2501\u2501\u2501\u2501\u2501\u2501\u2501\u2501\u2501\u2501\u2501\u2501\u2501\u2501\u2501\u2501\u2501\u2529\n\u2502     OTHER \u2502      44 \u2502         -0.1 \u2502        -146.442 \u2502        -1.46 \u2502      4:20:00 \u2502   14    26     4  31.8 \u2502\n\u2502     TOTAL \u2502      44 \u2502         -0.1 \u2502        -146.442 \u2502        -1.46 \u2502      4:20:00 \u2502   14    26     4  31.8 \u2502\n\u2514\u2500\u2500\u2500\u2500\u2500\u2500\u2500\u2500\u2500\u2500\u2500\u2534\u2500\u2500\u2500\u2500\u2500\u2500\u2500\u2500\u2500\u2534\u2500\u2500\u2500\u2500\u2500\u2500\u2500\u2500\u2500\u2500\u2500\u2500\u2500\u2500\u2534\u2500\u2500\u2500\u2500\u2500\u2500\u2500\u2500\u2500\u2500\u2500\u2500\u2500\u2500\u2500\u2500\u2500\u2534\u2500\u2500\u2500\u2500\u2500\u2500\u2500\u2500\u2500\u2500\u2500\u2500\u2500\u2500\u2534\u2500\u2500\u2500\u2500\u2500\u2500\u2500\u2500\u2500\u2500\u2500\u2500\u2500\u2500\u2534\u2500\u2500\u2500\u2500\u2500\u2500\u2500\u2500\u2500\u2500\u2500\u2500\u2500\u2500\u2500\u2500\u2500\u2500\u2500\u2500\u2500\u2500\u2500\u2500\u2518\n                                               EXIT REASON STATS                                               \n\u250f\u2501\u2501\u2501\u2501\u2501\u2501\u2501\u2501\u2501\u2501\u2501\u2501\u2501\u2533\u2501\u2501\u2501\u2501\u2501\u2501\u2501\u2533\u2501\u2501\u2501\u2501\u2501\u2501\u2501\u2501\u2501\u2501\u2501\u2501\u2501\u2501\u2533\u2501\u2501\u2501\u2501\u2501\u2501\u2501\u2501\u2501\u2501\u2501\u2501\u2501\u2501\u2501\u2501\u2501\u2533\u2501\u2501\u2501\u2501\u2501\u2501\u2501\u2501\u2501\u2501\u2501\u2501\u2501\u2501\u2533\u2501\u2501\u2501\u2501\u2501\u2501\u2501\u2501\u2501\u2501\u2501\u2501\u2501\u2501\u2533\u2501\u2501\u2501\u2501\u2501\u2501\u2501\u2501\u2501\u2501\u2501\u2501\u2501\u2501\u2501\u2501\u2501\u2501\u2501\u2501\u2501\u2501\u2501\u2501\u2513\n\u2503 Exit Reason \u2503 Exits \u2503 Avg Profit % \u2503 Tot Profit USDT \u2503 Tot Profit % \u2503 Avg Duration \u2503  Win  Draw  Loss  Win% \u2503\n\u2521\u2501\u2501\u2501\u2501\u2501\u2501\u2501\u2501\u2501\u2501\u2501\u2501\u2501\u2547\u2501\u2501\u2501\u2501\u2501\u2501\u2501\u2547\u2501\u2501\u2501\u2501\u2501\u2501\u2501\u2501\u2501\u2501\u2501\u2501\u2501\u2501\u2547\u2501\u2501\u2501\u2501\u2501\u2501\u2501\u2501\u2501\u2501\u2501\u2501\u2501\u2501\u2501\u2501\u2501\u2547\u2501\u2501\u2501\u2501\u2501\u2501\u2501\u2501\u2501\u2501\u2501\u2501\u2501\u2501\u2547\u2501\u2501\u2501\u2501\u2501\u2501\u2501\u2501\u2501\u2501\u2501\u2501\u2501\u2501\u2547\u2501\u2501\u2501\u2501\u2501\u2501\u2501\u2501\u2501\u2501\u2501\u2501\u2501\u2501\u2501\u2501\u2501\u2501\u2501\u2501\u2501\u2501\u2501\u2501\u2529\n\u2502         roi \u2502    40 \u2502         0.11 \u2502         142.951 \u2502         1.43 \u2502      3:53:00 \u2502   14    26     0   100 \u2502\n\u2502   stop_loss \u2502     4 \u2502         -2.2 \u2502        -289.393 \u2502        -2.89 \u2502      8:49:00 \u2502    0     0     4     0 \u2502\n\u2502       TOTAL \u2502    44 \u2502         -0.1 \u2502        -146.442 \u2502        -1.46 \u2502      4:20:00 \u2502   14    26     4  31.8 \u2502\n\u2514\u2500\u2500\u2500\u2500\u2500\u2500\u2500\u2500\u2500\u2500\u2500\u2500\u2500\u2534\u2500\u2500\u2500\u2500\u2500\u2500\u2500\u2534\u2500\u2500\u2500\u2500\u2500\u2500\u2500\u2500\u2500\u2500\u2500\u2500\u2500\u2500\u2534\u2500\u2500\u2500\u2500\u2500\u2500\u2500\u2500\u2500\u2500\u2500\u2500\u2500\u2500\u2500\u2500\u2500\u2534\u2500\u2500\u2500\u2500\u2500\u2500\u2500\u2500\u2500\u2500\u2500\u2500\u2500\u2500\u2534\u2500\u2500\u2500\u2500\u2500\u2500\u2500\u2500\u2500\u2500\u2500\u2500\u2500\u2500\u2534\u2500\u2500\u2500\u2500\u2500\u2500\u2500\u2500\u2500\u2500\u2500\u2500\u2500\u2500\u2500\u2500\u2500\u2500\u2500\u2500\u2500\u2500\u2500\u2500\u2518\n                                                      MIXED TAG STATS                                                       \n\u250f\u2501\u2501\u2501\u2501\u2501\u2501\u2501\u2501\u2501\u2501\u2501\u2533\u2501\u2501\u2501\u2501\u2501\u2501\u2501\u2501\u2501\u2501\u2501\u2501\u2501\u2533\u2501\u2501\u2501\u2501\u2501\u2501\u2501\u2501\u2533\u2501\u2501\u2501\u2501\u2501\u2501\u2501\u2501\u2501\u2501\u2501\u2501\u2501\u2501\u2533\u2501\u2501\u2501\u2501\u2501\u2501\u2501\u2501\u2501\u2501\u2501\u2501\u2501\u2501\u2501\u2501\u2501\u2533\u2501\u2501\u2501\u2501\u2501\u2501\u2501\u2501\u2501\u2501\u2501\u2501\u2501\u2501\u2533\u2501\u2501\u2501\u2501\u2501\u2501\u2501\u2501\u2501\u2501\u2501\u2501\u2501\u2501\u2533\u2501\u2501\u2501\u2501\u2501\u2501\u2501\u2501\u2501\u2501\u2501\u2501\u2501\u2501\u2501\u2501\u2501\u2501\u2501\u2501\u2501\u2501\u2501\u2501\u2513\n\u2503 Enter Tag \u2503 Exit Reason \u2503 Trades \u2503 Avg Profit % \u2503 Tot Profit USDT \u2503 Tot Profit % \u2503 Avg Duration \u2503  Win  Draw  Loss  Win% \u2503\n\u2521\u2501\u2501\u2501\u2501\u2501\u2501\u2501\u2501\u2501\u2501\u2501\u2547\u2501\u2501\u2501\u2501\u2501\u2501\u2501\u2501\u2501\u2501\u2501\u2501\u2501\u2547\u2501\u2501\u2501\u2501\u2501\u2501\u2501\u2501\u2547\u2501\u2501\u2501\u2501\u2501\u2501\u2501\u2501\u2501\u2501\u2501\u2501\u2501\u2501\u2547\u2501\u2501\u2501\u2501\u2501\u2501\u2501\u2501\u2501\u2501\u2501\u2501\u2501\u2501\u2501\u2501\u2501\u2547\u2501\u2501\u2501\u2501\u2501\u2501\u2501\u2501\u2501\u2501\u2501\u2501\u2501\u2501\u2547\u2501\u2501\u2501\u2501\u2501\u2501\u2501\u2501\u2501\u2501\u2501\u2501\u2501\u2501\u2547\u2501\u2501\u2501\u2501\u2501\u2501\u2501\u2501\u2501\u2501\u2501\u2501\u2501\u2501\u2501\u2501\u2501\u2501\u2501\u2501\u2501\u2501\u2501\u2501\u2529\n\u2502           \u2502         roi \u2502     40 \u2502         0.11 \u2502         142.951 \u2502         1.43 \u2502      3:53:00 \u2502   14    26     0   100 \u2502\n\u2502           \u2502   stop_loss \u2502      4 \u2502         -2.2 \u2502        -289.393 \u2502        -2.89 \u2502      8:49:00 \u2502    0     0     4     0 \u2502\n\u2502     TOTAL \u2502             \u2502     44 \u2502         -0.1 \u2502        -146.442 \u2502        -1.46 \u2502      4:20:00 \u2502   14    26     4  31.8 \u2502\n\u2514\u2500\u2500\u2500\u2500\u2500\u2500\u2500\u2500\u2500\u2500\u2500\u2534\u2500\u2500\u2500\u2500\u2500\u2500\u2500\u2500\u2500\u2500\u2500\u2500\u2500\u2534\u2500\u2500\u2500\u2500\u2500\u2500\u2500\u2500\u2534\u2500\u2500\u2500\u2500\u2500\u2500\u2500\u2500\u2500\u2500\u2500\u2500\u2500\u2500\u2534\u2500\u2500\u2500\u2500\u2500\u2500\u2500\u2500\u2500\u2500\u2500\u2500\u2500\u2500\u2500\u2500\u2500\u2534\u2500\u2500\u2500\u2500\u2500\u2500\u2500\u2500\u2500\u2500\u2500\u2500\u2500\u2500\u2534\u2500\u2500\u2500\u2500\u2500\u2500\u2500\u2500\u2500\u2500\u2500\u2500\u2500\u2500\u2534\u2500\u2500\u2500\u2500\u2500\u2500\u2500\u2500\u2500\u2500\u2500\u2500\u2500\u2500\u2500\u2500\u2500\u2500\u2500\u2500\u2500\u2500\u2500\u2500\u2518\n                         SUMMARY METRICS                          \n\u250f\u2501\u2501\u2501\u2501\u2501\u2501\u2501\u2501\u2501\u2501\u2501\u2501\u2501\u2501\u2501\u2501\u2501\u2501\u2501\u2501\u2501\u2501\u2501\u2501\u2501\u2501\u2501\u2501\u2501\u2501\u2501\u2533\u2501\u2501\u2501\u2501\u2501\u2501\u2501\u2501\u2501\u2501\u2501\u2501\u2501\u2501\u2501\u2501\u2501\u2501\u2501\u2501\u2501\u2501\u2501\u2501\u2501\u2501\u2501\u2501\u2501\u2501\u2501\u2501\u2513\n\u2503 Metric                        \u2503 Value                          \u2503\n\u2521\u2501\u2501\u2501\u2501\u2501\u2501\u2501\u2501\u2501\u2501\u2501\u2501\u2501\u2501\u2501\u2501\u2501\u2501\u2501\u2501\u2501\u2501\u2501\u2501\u2501\u2501\u2501\u2501\u2501\u2501\u2501\u2547\u2501\u2501\u2501\u2501\u2501\u2501\u2501\u2501\u2501\u2501\u2501\u2501\u2501\u2501\u2501\u2501\u2501\u2501\u2501\u2501\u2501\u2501\u2501\u2501\u2501\u2501\u2501\u2501\u2501\u2501\u2501\u2501\u2529\n\u2502 Backtesting from              \u2502 2025-02-02 02:30:00            \u2502\n\u2502 Backtesting to                \u2502 2026-02-03 00:00:00            \u2502\n\u2502 Trading Mode                  \u2502 Spot                           \u2502\n\u2502 Max open trades               \u2502 1                              \u2502\n\u2502                               \u2502                                \u2502\n\u2502 Total/Daily Avg Trades        \u2502 44 / 0.12                      \u2502\n\u2502 Starting balance              \u2502 10000 USDT                     \u2502\n\u2502 Final balance                 \u2502 9853.558 USDT                  \u2502\n\u2502 Absolute profit               \u2502 -146.442 USDT                  \u2502\n\u2502 Total profit %                \u2502 -1.46%                         \u2502\n\u2502 CAGR %                        \u2502 -1.46%                         \u2502\n\u2502 Sortino                       \u2502 -18.12                         \u2502\n\u2502 Sharpe                        \u2502 -0.34                          \u2502\n\u2502 Calmar                        \u2502 -3.44                          \u2502\n\u2502 SQN                           \u2502 -0.96                          \u2502\n\u2502 Profit factor                 \u2502 0.49                           \u2502\n\u2502 Expectancy (Ratio)            \u2502 -3.33 (-0.64)                  \u2502\n\u2502 Avg. daily profit             \u2502 -0.401 USDT                    \u2502\n\u2502 Avg. stake amount             \u2502 3284.994 USDT                  \u2502\n\u2502 Total trade volume            \u2502 289511.478 USDT                \u2502\n\u2502                               \u2502                                \u2502\n\u2502 Best Pair                     \u2502 BTC/USDT -1.46%                \u2502\n\u2502 Worst Pair                    \u2502 BTC/USDT -1.46%                \u2502\n\u2502 Best trade                    \u2502 BTC/USDT 1.00%                 \u2502\n\u2502 Worst trade                   \u2502 BTC/USDT -2.20%                \u2502\n\u2502 Best day                      \u2502 32.41 USDT                     \u2502\n\u2502 Worst day                     \u2502 -72.859 USDT                   \u2502\n\u2502 Days win/draw/lose            \u2502 14 / 337 / 4                   \u2502\n\u2502 Min/Max/Avg. Duration Winners \u2502 0d 00:10 / 0d 01:00 / 0d 00:50 \u2502\n\u2502 Min/Max/Avg. Duration Losers  \u2502 0d 03:25 / 0d 14:45 / 0d 08:49 \u2502\n\u2502 Max Consecutive Wins / Loss   \u2502 3 / 8                          \u2502\n\u2502 Rejected Entry signals        \u2502 0                              \u2502\n\u2502 Entry/Exit Timeouts           \u2502 0 / 0                          \u2502\n\u2502                               \u2502                                \u2502\n\u2502 Min balance                   \u2502 9821.148 USDT                  \u2502\n\u2502 Max balance                   \u2502 10045.143 USDT                 \u2502\n\u2502 Max % of account underwater   \u2502 2.23%                          \u2502\n\u2502 Absolute drawdown             \u2502 223.995 USDT (2.23%)           \u2502\n\u2502 Drawdown duration             \u2502 291 days 00:45:00              \u2502\n\u2502 Profit at drawdown start      \u2502 45.143 USDT                    \u2502\n\u2502 Profit at drawdown end        \u2502 -178.852 USDT                  \u2502\n\u2502 Drawdown start                \u2502 2025-04-16 14:30:00            \u2502\n\u2502 Drawdown end                  \u2502 2026-02-01 15:15:00            \u2502\n\u2502 Market change                 \u2502 -22.14%                        \u2502\n\u2514\u2500\u2500\u2500\u2500\u2500\u2500\u2500\u2500\u2500\u2500\u2500\u2500\u2500\u2500\u2500\u2500\u2500\u2500\u2500\u2500\u2500\u2500\u2500\u2500\u2500\u2500\u2500\u2500\u2500\u2500\u2500\u2534\u2500\u2500\u2500\u2500\u2500\u2500\u2500\u2500\u2500\u2500\u2500\u2500\u2500\u2500\u2500\u2500\u2500\u2500\u2500\u2500\u2500\u2500\u2500\u2500\u2500\u2500\u2500\u2500\u2500\u2500\u2500\u2500\u2518\n\nBacktested 2025-02-02 02:30:00 -> 2026-02-03 00:00:00 | Max open trades : 1\n                                                              STRATEGY SUMMARY                                                               \n\u250f\u2501\u2501\u2501\u2501\u2501\u2501\u2501\u2501\u2501\u2501\u2501\u2501\u2501\u2501\u2501\u2501\u2501\u2501\u2501\u2501\u2533\u2501\u2501\u2501\u2501\u2501\u2501\u2501\u2501\u2533\u2501\u2501\u2501\u2501\u2501\u2501\u2501\u2501\u2501\u2501\u2501\u2501\u2501\u2501\u2533\u2501\u2501\u2501\u2501\u2501\u2501\u2501\u2501\u2501\u2501\u2501\u2501\u2501\u2501\u2501\u2501\u2501\u2533\u2501\u2501\u2501\u2501\u2501\u2501\u2501\u2501\u2501\u2501\u2501\u2501\u2501\u2501\u2533\u2501\u2501\u2501\u2501\u2501\u2501\u2501\u2501\u2501\u2501\u2501\u2501\u2501\u2501\u2533\u2501\u2501\u2501\u2501\u2501\u2501\u2501\u2501\u2501\u2501\u2501\u2501\u2501\u2501\u2501\u2501\u2501\u2501\u2501\u2501\u2501\u2501\u2501\u2501\u2533\u2501\u2501\u2501\u2501\u2501\u2501\u2501\u2501\u2501\u2501\u2501\u2501\u2501\u2501\u2501\u2501\u2501\u2501\u2501\u2501\u2501\u2513\n\u2503           Strategy \u2503 Trades \u2503 Avg Profit % \u2503 Tot Profit USDT \u2503 Tot Profit % \u2503 Avg Duration \u2503  Win  Draw  Loss  Win% \u2503            Drawdown \u2503\n\u2521\u2501\u2501\u2501\u2501\u2501\u2501\u2501\u2501\u2501\u2501\u2501\u2501\u2501\u2501\u2501\u2501\u2501\u2501\u2501\u2501\u2547\u2501\u2501\u2501\u2501\u2501\u2501\u2501\u2501\u2547\u2501\u2501\u2501\u2501\u2501\u2501\u2501\u2501\u2501\u2501\u2501\u2501\u2501\u2501\u2547\u2501\u2501\u2501\u2501\u2501\u2501\u2501\u2501\u2501\u2501\u2501\u2501\u2501\u2501\u2501\u2501\u2501\u2547\u2501\u2501\u2501\u2501\u2501\u2501\u2501\u2501\u2501\u2501\u2501\u2501\u2501\u2501\u2547\u2501\u2501\u2501\u2501\u2501\u2501\u2501\u2501\u2501\u2501\u2501\u2501\u2501\u2501\u2547\u2501\u2501\u2501\u2501\u2501\u2501\u2501\u2501\u2501\u2501\u2501\u2501\u2501\u2501\u2501\u2501\u2501\u2501\u2501\u2501\u2501\u2501\u2501\u2501\u2547\u2501\u2501\u2501\u2501\u2501\u2501\u2501\u2501\u2501\u2501\u2501\u2501\u2501\u2501\u2501\u2501\u2501\u2501\u2501\u2501\u2501\u2529\n\u2502 BTCMomentumScalper \u2502     44 \u2502        -0.10 \u2502        -146.442 \u2502        -1.46 \u2502      4:20:00 \u2502   14    26     4  31.8 \u2502 223.995 USDT  2.23% \u2502\n\u2514\u2500\u2500\u2500\u2500\u2500\u2500\u2500\u2500\u2500\u2500\u2500\u2500\u2500\u2500\u2500\u2500\u2500\u2500\u2500\u2500\u2534\u2500\u2500\u2500\u2500\u2500\u2500\u2500\u2500\u2534\u2500\u2500\u2500\u2500\u2500\u2500\u2500\u2500\u2500\u2500\u2500\u2500\u2500\u2500\u2534\u2500\u2500\u2500\u2500\u2500\u2500\u2500\u2500\u2500\u2500\u2500\u2500\u2500\u2500\u2500\u2500\u2500\u2534\u2500\u2500\u2500\u2500\u2500\u2500\u2500\u2500\u2500\u2500\u2500\u2500\u2500\u2500\u2534\u2500\u2500\u2500\u2500\u2500\u2500\u2500\u2500\u2500\u2500\u2500\u2500\u2500\u2500\u2534\u2500\u2500\u2500\u2500\u2500\u2500\u2500\u2500\u2500\u2500\u2500\u2500\u2500\u2500\u2500\u2500\u2500\u2500\u2500\u2500\u2500\u2500\u2500\u2500\u2534\u2500\u2500\u2500\u2500\u2500\u2500\u2500\u2500\u2500\u2500\u2500\u2500\u2500\u2500\u2500\u2500\u2500\u2500\u2500\u2500\u2500\u2518\n2026-02-02 19:47:14,904 - freqtrade - INFO - freqtrade 2026.1\n2026-02-02 19:47:16,508 - freqtrade.configuration.load_config - INFO - Using config: config/config.json ...\n2026-02-02 19:47:16,510 - freqtrade.loggers - INFO - Enabling colorized output.\n2026-02-02 19:47:16,511 - freqtrade.loggers - INFO - Logfile configured\n2026-02-02 19:47:16,511 - freqtrade.loggers - INFO - Verbosity set to 0\n2026-02-02 19:47:16,511 - freqtrade.configuration.configuration - INFO - Using additional Strategy lookup path: strategies/btc_momentum_scalper/\n2026-02-02 19:47:16,511 - freqtrade.configuration.configuration - INFO - Using max_open_trades: 3 ...\n2026-02-02 19:47:16,511 - freqtrade.configuration.configuration - INFO - Parameter --timerange detected: 20250202-20260203 ...\n2026-02-02 19:47:16,512 - freqtrade.configuration.configuration - INFO - Using user-data directory: /Users/naynay/Projects/personal/backtest-strat/user_data ...\n2026-02-02 19:47:16,512 - freqtrade.configuration.configuration - INFO - Using data directory: /Users/naynay/Projects/personal/backtest-strat/user_data/data/bybit ...\n2026-02-02 19:47:16,512 - freqtrade.configuration.configuration - INFO - Parameter --cache=day detected ...\n2026-02-02 19:47:16,512 - freqtrade.configuration.configuration - INFO - Filter trades by timerange: 20250202-20260203\n2026-02-02 19:47:16,513 - freqtrade.exchange.check_exchange - INFO - Checking exchange...\n2026-02-02 19:47:16,517 - freqtrade.exchange.check_exchange - INFO - Exchange \"bybit\" is officially supported by the Freqtrade development team.\n2026-02-02 19:47:16,517 - freqtrade.configuration.configuration - INFO - Using pairlist from configuration.\n2026-02-02 19:47:16,518 - freqtrade.configuration.config_validation - INFO - Validating configuration ...\n2026-02-02 19:47:16,519 - freqtrade.commands.optimize_commands - INFO - Starting freqtrade in Backtesting mode\n2026-02-02 19:47:16,519 - freqtrade.exchange.exchange - INFO - Instance is running with dry_run enabled\n2026-02-02 19:47:16,520 - freqtrade.exchange.exchange - INFO - Using CCXT 4.5.35\n2026-02-02 19:47:16,520 - freqtrade.exchange.exchange - INFO - Applying additional ccxt config: {'options': {'defaultType': 'spot'}}\n2026-02-02 19:47:16,523 - freqtrade.exchange.exchange - INFO - Applying additional ccxt config: {'options': {'defaultType': 'spot'}}\n2026-02-02 19:47:16,527 - freqtrade.exchange.exchange - INFO - Using Exchange \"Bybit\"\n2026-02-02 19:47:18,440 - freqtrade.resolvers.exchange_resolver - INFO - Using resolved exchange 'Bybit'...\n2026-02-02 19:47:18,458 - freqtrade.resolvers.iresolver - INFO - Using resolved strategy BTCMomentumScalper from \n'/Users/naynay/Projects/personal/backtest-strat/strategies/btc_momentum_scalper/strategy.py'...\n2026-02-02 19:47:18,459 - freqtrade.strategy.hyper - INFO - Found no parameter file.\n2026-02-02 19:47:18,459 - freqtrade.resolvers.strategy_resolver - INFO - Override strategy 'stake_currency' with value from the configuration: USDT.\n2026-02-02 19:47:18,459 - freqtrade.resolvers.strategy_resolver - INFO - Override strategy 'stake_amount' with value from the configuration: unlimited.\n2026-02-02 19:47:18,460 - freqtrade.resolvers.strategy_resolver - INFO - Override strategy 'unfilledtimeout' with value from the configuration: {'entry': 10, 'exit': 10, 'exit_timeout_count': 0, \n'unit': 'minutes'}.\n2026-02-02 19:47:18,460 - freqtrade.resolvers.strategy_resolver - INFO - Override strategy 'use_exit_signal' with value from the configuration: False.\n2026-02-02 19:47:18,460 - freqtrade.resolvers.strategy_resolver - INFO - Override strategy 'max_open_trades' with value from the configuration: 3.\n2026-02-02 19:47:18,460 - freqtrade.resolvers.strategy_resolver - INFO - Strategy using minimal_roi: {'0': 0.01, '30': 0.005, '60': 0.0}\n2026-02-02 19:47:18,460 - freqtrade.resolvers.strategy_resolver - INFO - Strategy using timeframe: 5m\n2026-02-02 19:47:18,460 - freqtrade.resolvers.strategy_resolver - INFO - Strategy using stoploss: -0.02\n2026-02-02 19:47:18,461 - freqtrade.resolvers.strategy_resolver - INFO - Strategy using trailing_stop: True\n2026-02-02 19:47:18,461 - freqtrade.resolvers.strategy_resolver - INFO - Strategy using trailing_stop_positive: 0.005\n2026-02-02 19:47:18,461 - freqtrade.resolvers.strategy_resolver - INFO - Strategy using trailing_stop_positive_offset: 0.01\n2026-02-02 19:47:18,461 - freqtrade.resolvers.strategy_resolver - INFO - Strategy using trailing_only_offset_is_reached: True\n2026-02-02 19:47:18,461 - freqtrade.resolvers.strategy_resolver - INFO - Strategy using use_custom_stoploss: False\n2026-02-02 19:47:18,461 - freqtrade.resolvers.strategy_resolver - INFO - Strategy using process_only_new_candles: True\n2026-02-02 19:47:18,461 - freqtrade.resolvers.strategy_resolver - INFO - Strategy using order_types: {'entry': 'limit', 'exit': 'limit', 'stoploss': 'market', 'stoploss_on_exchange': False}\n2026-02-02 19:47:18,461 - freqtrade.resolvers.strategy_resolver - INFO - Strategy using order_time_in_force: {'entry': 'GTC', 'exit': 'GTC'}\n2026-02-02 19:47:18,462 - freqtrade.resolvers.strategy_resolver - INFO - Strategy using stake_currency: USDT\n2026-02-02 19:47:18,462 - freqtrade.resolvers.strategy_resolver - INFO - Strategy using stake_amount: unlimited\n2026-02-02 19:47:18,462 - freqtrade.resolvers.strategy_resolver - INFO - Strategy using startup_candle_count: 30\n2026-02-02 19:47:18,462 - freqtrade.resolvers.strategy_resolver - INFO - Strategy using unfilledtimeout: {'entry': 10, 'exit': 10, 'exit_timeout_count': 0, 'unit': 'minutes'}\n2026-02-02 19:47:18,462 - freqtrade.resolvers.strategy_resolver - INFO - Strategy using use_exit_signal: False\n2026-02-02 19:47:18,462 - freqtrade.resolvers.strategy_resolver - INFO - Strategy using exit_profit_only: False\n2026-02-02 19:47:18,462 - freqtrade.resolvers.strategy_resolver - INFO - Strategy using ignore_roi_if_entry_signal: False\n2026-02-02 19:47:18,463 - freqtrade.resolvers.strategy_resolver - INFO - Strategy using exit_profit_offset: 0.0\n2026-02-02 19:47:18,463 - freqtrade.resolvers.strategy_resolver - INFO - Strategy using disable_dataframe_checks: False\n2026-02-02 19:47:18,463 - freqtrade.resolvers.strategy_resolver - INFO - Strategy using ignore_buying_expired_candle_after: 0\n2026-02-02 19:47:18,463 - freqtrade.resolvers.strategy_resolver - INFO - Strategy using position_adjustment_enable: False\n2026-02-02 19:47:18,463 - freqtrade.resolvers.strategy_resolver - INFO - Strategy using max_entry_position_adjustment: -1\n2026-02-02 19:47:18,463 - freqtrade.resolvers.strategy_resolver - INFO - Strategy using max_open_trades: 3\n2026-02-02 19:47:18,463 - freqtrade.configuration.config_validation - INFO - Validating configuration ...\n2026-02-02 19:47:18,469 - freqtrade.resolvers.iresolver - INFO - Using resolved pairlist StaticPairList from \n'/Users/naynay/Projects/personal/backtest-strat/.venv/lib/python3.11/site-packages/freqtrade/plugins/pairlist/StaticPairList.py'...\n2026-02-02 19:47:18,472 - freqtrade.optimize.backtesting - INFO - Using fee 0.1000% - worst case fee from exchange (lowest tier).\n2026-02-02 19:47:18,562 - freqtrade.data.history.datahandlers.idatahandler - WARNING - BTC/USDT, spot, 5m, data starts at 2025-02-02 00:00:00\n2026-02-02 19:47:18,607 - freqtrade.optimize.backtesting - INFO - Loading data from 2025-02-02 00:00:00 up to 2026-02-03 00:00:00 (366 days).\n2026-02-02 19:47:18,607 - freqtrade.configuration.timerange - WARNING - Moving start-date by 30 candles to account for startup time.\n2026-02-02 19:47:19,145 - freqtrade.optimize.backtesting - INFO - Dataload complete. Calculating indicators\n2026-02-02 19:47:19,147 - freqtrade.optimize.backtesting - INFO - Running backtesting for Strategy BTCMomentumScalper\n2026-02-02 19:47:19,148 - freqtrade.strategy.hyper - INFO - No params for buy found, using default values.\n2026-02-02 19:47:19,148 - freqtrade.strategy.hyper - INFO - Strategy Parameter(default): buy_ema_long = 21\n2026-02-02 19:47:19,148 - freqtrade.strategy.hyper - INFO - Strategy Parameter(default): buy_ema_short = 9\n2026-02-02 19:47:19,149 - freqtrade.strategy.hyper - INFO - Strategy Parameter(default): buy_rsi_max = 70\n2026-02-02 19:47:19,149 - freqtrade.strategy.hyper - INFO - Strategy Parameter(default): buy_volume_factor = 1.0\n2026-02-02 19:47:19,149 - freqtrade.strategy.hyper - INFO - No params for sell found, using default values.\n2026-02-02 19:47:19,149 - freqtrade.strategy.hyper - INFO - Strategy Parameter(default): sell_rsi_max = 80\n2026-02-02 19:47:19,175 - freqtrade.optimize.backtesting - INFO - Backtesting with data from 2025-02-02 02:30:00 up to 2026-02-03 00:00:00 (365 days).\n2026-02-02 19:47:20,118 - freqtrade.misc - INFO - dumping json to \"/Users/naynay/Projects/personal/backtest-strat/user_data/backtest_results/backtest-result-2026-02-02_19-47-20.meta.json\"\n",
  "market_change": "-22.14%",
  "trades": "44",
  "avg_profit_pct": "-0.10",
  "total_profit_usdt": "-146.442",
  "total_profit_pct": "-1.46",
  "avg_duration": "4:20:00",
  "win_draw_loss": "14    26     4  31.8",
  "drawdown": "223.995 USDT  2.23%",
  "name": "all_data_1yr"
}